{
"meta":{"test_sets":[],"test_metrics":[],"learn_metrics":[{"best_value":"Min","name":"Logloss"}],"launch_mode":"Train","parameters":"","iteration_count":1000,"learn_sets":["learn"],"name":"experiment"},
"iterations":[
{"learn":[0.58772222],"iteration":0,"passed_time":0.07602142353,"remaining_time":75.94540211},
{"learn":[0.4949682571],"iteration":1,"passed_time":0.1366924861,"remaining_time":68.20955054},
{"learn":[0.4231878779],"iteration":2,"passed_time":0.202528729,"remaining_time":67.30704759},
{"learn":[0.3635654236],"iteration":3,"passed_time":0.2553689879,"remaining_time":63.586878},
{"learn":[0.3198206727],"iteration":4,"passed_time":0.3248083037,"remaining_time":64.63685244},
{"learn":[0.2781249857],"iteration":5,"passed_time":0.3767257763,"remaining_time":62.4109036},
{"learn":[0.248785485],"iteration":6,"passed_time":0.4479384458,"remaining_time":63.54326809},
{"learn":[0.2206378664],"iteration":7,"passed_time":0.5167340506,"remaining_time":64.07502227},
{"learn":[0.2020420177],"iteration":8,"passed_time":0.5726027358,"remaining_time":63.04992347},
{"learn":[0.18222896],"iteration":9,"passed_time":0.6310451076,"remaining_time":62.47346565},
{"learn":[0.1674483312],"iteration":10,"passed_time":0.6860159537,"remaining_time":61.67907075},
{"learn":[0.1508600842],"iteration":11,"passed_time":0.752514865,"remaining_time":61.95705722},
{"learn":[0.1359417557],"iteration":12,"passed_time":0.8667510422,"remaining_time":65.80640605},
{"learn":[0.1261218524],"iteration":13,"passed_time":0.9337430495,"remaining_time":65.76218906},
{"learn":[0.1156498479],"iteration":14,"passed_time":1.01620428,"remaining_time":66.73074774},
{"learn":[0.1048069812],"iteration":15,"passed_time":1.114167704,"remaining_time":68.52131381},
{"learn":[0.09567486688],"iteration":16,"passed_time":1.177564357,"remaining_time":68.09092722},
{"learn":[0.08815418106],"iteration":17,"passed_time":1.3021999,"remaining_time":71.04223899},
{"learn":[0.08158342925],"iteration":18,"passed_time":1.364490316,"remaining_time":70.45078947},
{"learn":[0.07536986142],"iteration":19,"passed_time":1.470954779,"remaining_time":72.07678418},
{"learn":[0.07031690909],"iteration":20,"passed_time":1.548790222,"remaining_time":72.20312513},
{"learn":[0.06634178637],"iteration":21,"passed_time":1.62415347,"remaining_time":72.20100425},
{"learn":[0.06224631271],"iteration":22,"passed_time":1.682804832,"remaining_time":71.48262264},
{"learn":[0.05913936647],"iteration":23,"passed_time":1.748975669,"remaining_time":71.12501055},
{"learn":[0.05562626878],"iteration":24,"passed_time":1.824010171,"remaining_time":71.13639667},
{"learn":[0.0530961755],"iteration":25,"passed_time":1.890116132,"remaining_time":70.80665817},
{"learn":[0.05088778998],"iteration":26,"passed_time":1.938564596,"remaining_time":69.86012414},
{"learn":[0.0487282994],"iteration":27,"passed_time":2.013090996,"remaining_time":69.883016},
{"learn":[0.04692369182],"iteration":28,"passed_time":2.09084136,"remaining_time":70.00713658},
{"learn":[0.044987573],"iteration":29,"passed_time":2.168305066,"remaining_time":70.10853046},
{"learn":[0.04387043046],"iteration":30,"passed_time":2.231432833,"remaining_time":69.75027147},
{"learn":[0.04169373097],"iteration":31,"passed_time":2.292392218,"remaining_time":69.34486459},
{"learn":[0.04057199406],"iteration":32,"passed_time":2.346801218,"remaining_time":68.76838721},
{"learn":[0.03856533925],"iteration":33,"passed_time":2.40450767,"remaining_time":68.31630615},
{"learn":[0.03724933669],"iteration":34,"passed_time":2.486782679,"remaining_time":68.56415101},
{"learn":[0.0355840984],"iteration":35,"passed_time":2.547017084,"remaining_time":68.20345748},
{"learn":[0.03452639626],"iteration":36,"passed_time":2.625117684,"remaining_time":68.32400892},
{"learn":[0.03367358515],"iteration":37,"passed_time":2.686390627,"remaining_time":68.00809957},
{"learn":[0.03272751414],"iteration":38,"passed_time":2.765830371,"remaining_time":68.15289709},
{"learn":[0.03186793202],"iteration":39,"passed_time":2.83000779,"remaining_time":67.92018695},
{"learn":[0.03116782313],"iteration":40,"passed_time":2.891481312,"remaining_time":67.63245312},
{"learn":[0.03049843254],"iteration":41,"passed_time":2.955277705,"remaining_time":67.40847717},
{"learn":[0.02983099046],"iteration":42,"passed_time":3.015405584,"remaining_time":67.11030568},
{"learn":[0.02906913904],"iteration":43,"passed_time":3.078765776,"remaining_time":66.89318368},
{"learn":[0.02818566317],"iteration":44,"passed_time":3.145203201,"remaining_time":66.74820127},
{"learn":[0.02775510766],"iteration":45,"passed_time":3.203902959,"remaining_time":66.44616138},
{"learn":[0.02734587427],"iteration":46,"passed_time":3.278872548,"remaining_time":66.48437315},
{"learn":[0.02674978564],"iteration":47,"passed_time":3.347324179,"remaining_time":66.38859622},
{"learn":[0.02635790922],"iteration":48,"passed_time":3.391060432,"remaining_time":65.81425451},
{"learn":[0.02604548684],"iteration":49,"passed_time":3.446111091,"remaining_time":65.47611074},
{"learn":[0.02578999792],"iteration":50,"passed_time":3.508657687,"remaining_time":65.28855185},
{"learn":[0.02535008423],"iteration":51,"passed_time":3.559978759,"remaining_time":64.90115123},
{"learn":[0.02487778319],"iteration":52,"passed_time":3.621095385,"remaining_time":64.70145905},
{"learn":[0.024251394],"iteration":53,"passed_time":3.680212125,"remaining_time":64.47186427},
{"learn":[0.0238126935],"iteration":54,"passed_time":3.737013509,"remaining_time":64.20868665},
{"learn":[0.02348961653],"iteration":55,"passed_time":3.799105918,"remaining_time":64.0420712},
{"learn":[0.02296816426],"iteration":56,"passed_time":3.865687526,"remaining_time":63.95339187},
{"learn":[0.02250743054],"iteration":57,"passed_time":3.923074446,"remaining_time":63.71614015},
{"learn":[0.0221979668],"iteration":58,"passed_time":3.984930236,"remaining_time":63.5562602},
{"learn":[0.02190068313],"iteration":59,"passed_time":4.061492066,"remaining_time":63.63004236},
{"learn":[0.02163182966],"iteration":60,"passed_time":4.116985484,"remaining_time":63.37457983},
{"learn":[0.02144317967],"iteration":61,"passed_time":4.164450489,"remaining_time":63.00410578},
{"learn":[0.02119094124],"iteration":62,"passed_time":4.231382894,"remaining_time":62.93342494},
{"learn":[0.02106811258],"iteration":63,"passed_time":4.305665517,"remaining_time":62.97035819},
{"learn":[0.02072627313],"iteration":64,"passed_time":4.368632454,"remaining_time":62.84109761},
{"learn":[0.02034994036],"iteration":65,"passed_time":4.432669333,"remaining_time":62.72898723},
{"learn":[0.0200139279],"iteration":66,"passed_time":4.496672598,"remaining_time":62.61784379},
{"learn":[0.01973841933],"iteration":67,"passed_time":4.554710898,"remaining_time":62.42633171},
{"learn":[0.01964470155],"iteration":68,"passed_time":4.625086745,"remaining_time":62.40515594},
{"learn":[0.01942187637],"iteration":69,"passed_time":4.685011359,"remaining_time":62.24372235},
{"learn":[0.01923396371],"iteration":70,"passed_time":4.752503148,"remaining_time":62.1841609},
{"learn":[0.01900606787],"iteration":71,"passed_time":4.811038278,"remaining_time":62.0089378},
{"learn":[0.01877655195],"iteration":72,"passed_time":4.872123912,"remaining_time":61.86929953},
{"learn":[0.01843235005],"iteration":73,"passed_time":4.948649307,"remaining_time":61.92498998},
{"learn":[0.01827954719],"iteration":74,"passed_time":5.003197662,"remaining_time":61.7061045},
{"learn":[0.01798645084],"iteration":75,"passed_time":5.077913187,"remaining_time":61.73673402},
{"learn":[0.01779184913],"iteration":76,"passed_time":5.160735681,"remaining_time":61.86180563},
{"learn":[0.01762543077],"iteration":77,"passed_time":5.214577318,"remaining_time":61.63897804},
{"learn":[0.01730162632],"iteration":78,"passed_time":5.270021526,"remaining_time":61.43911171},
{"learn":[0.0172005303],"iteration":79,"passed_time":5.319869036,"remaining_time":61.17849391},
{"learn":[0.01714420897],"iteration":80,"passed_time":5.387145575,"remaining_time":61.12082449},
{"learn":[0.01708384957],"iteration":81,"passed_time":5.445867435,"remaining_time":60.96715007},
{"learn":[0.01693390159],"iteration":82,"passed_time":5.502031074,"remaining_time":60.78749994},
{"learn":[0.01682246464],"iteration":83,"passed_time":5.549285258,"remaining_time":60.51363448},
{"learn":[0.01671829204],"iteration":84,"passed_time":5.604689271,"remaining_time":60.33283156},
{"learn":[0.01652505301],"iteration":85,"passed_time":5.677198231,"remaining_time":60.33673468},
{"learn":[0.0163695501],"iteration":86,"passed_time":5.741706049,"remaining_time":60.25491521},
{"learn":[0.01625784289],"iteration":87,"passed_time":5.793178096,"remaining_time":60.03839118},
{"learn":[0.01614664632],"iteration":88,"passed_time":5.852525013,"remaining_time":59.906183},
{"learn":[0.01604850299],"iteration":89,"passed_time":5.909789279,"remaining_time":59.75453605},
{"learn":[0.01598398245],"iteration":90,"passed_time":5.970443606,"remaining_time":59.63882679},
{"learn":[0.0159200712],"iteration":91,"passed_time":6.059296427,"remaining_time":59.80262125},
{"learn":[0.0157641871],"iteration":92,"passed_time":6.112201386,"remaining_time":59.61039416},
{"learn":[0.01564288559],"iteration":93,"passed_time":6.171279801,"remaining_time":59.48063298},
{"learn":[0.0154836634],"iteration":94,"passed_time":6.238987164,"remaining_time":59.43456193},
{"learn":[0.01531496397],"iteration":95,"passed_time":6.288313268,"remaining_time":59.21494994},
{"learn":[0.01520677873],"iteration":96,"passed_time":6.355257522,"remaining_time":59.16286127},
{"learn":[0.01508453535],"iteration":97,"passed_time":6.408689749,"remaining_time":58.98610361},
{"learn":[0.01490829065],"iteration":98,"passed_time":6.478206819,"remaining_time":58.9582257},
{"learn":[0.01484021216],"iteration":99,"passed_time":6.524833968,"remaining_time":58.72350571},
{"learn":[0.01480814453],"iteration":100,"passed_time":6.587008225,"remaining_time":58.63089499},
{"learn":[0.0147204117],"iteration":101,"passed_time":6.640221985,"remaining_time":58.45999356},
{"learn":[0.01458661161],"iteration":102,"passed_time":6.704968102,"remaining_time":58.39180958},
{"learn":[0.01455819972],"iteration":103,"passed_time":6.77559222,"remaining_time":58.37433298},
{"learn":[0.01451199144],"iteration":104,"passed_time":6.830942605,"remaining_time":58.22565364},
{"learn":[0.01443740697],"iteration":105,"passed_time":6.892184787,"remaining_time":58.12842641},
{"learn":[0.01437594458],"iteration":106,"passed_time":6.951939652,"remaining_time":58.01945896},
{"learn":[0.0143395349],"iteration":107,"passed_time":7.020170066,"remaining_time":57.98140462},
{"learn":[0.01421076073],"iteration":108,"passed_time":7.079861203,"remaining_time":57.87299387},
{"learn":[0.01410587686],"iteration":109,"passed_time":7.135328255,"remaining_time":57.73129224},
{"learn":[0.01409037155],"iteration":110,"passed_time":7.19828162,"remaining_time":57.65110234},
{"learn":[0.01401729858],"iteration":111,"passed_time":7.26906091,"remaining_time":57.63326864},
{"learn":[0.01398329115],"iteration":112,"passed_time":7.332032844,"remaining_time":57.55321356},
{"learn":[0.01386443009],"iteration":113,"passed_time":7.390284386,"remaining_time":57.43677163},
{"learn":[0.0136989333],"iteration":114,"passed_time":7.444888177,"remaining_time":57.29326989},
{"learn":[0.01361826869],"iteration":115,"passed_time":7.496577694,"remaining_time":57.12909208},
{"learn":[0.0135645201],"iteration":116,"passed_time":7.552582216,"remaining_time":56.99940254},
{"learn":[0.01347009106],"iteration":117,"passed_time":7.620079268,"remaining_time":56.95686368},
{"learn":[0.01339151616],"iteration":118,"passed_time":7.678914408,"remaining_time":56.8497781},
{"learn":[0.01329507597],"iteration":119,"passed_time":7.739785163,"remaining_time":56.75842453},
{"learn":[0.01319168094],"iteration":120,"passed_time":7.794691277,"remaining_time":56.6242449},
{"learn":[0.01316734989],"iteration":121,"passed_time":7.85516465,"remaining_time":56.53143085},
{"learn":[0.01309679014],"iteration":122,"passed_time":7.916474798,"remaining_time":56.44510893},
{"learn":[0.01300121967],"iteration":123,"passed_time":7.973534747,"remaining_time":56.32916482},
{"learn":[0.01298448784],"iteration":124,"passed_time":8.027351585,"remaining_time":56.19146109},
{"learn":[0.01287030657],"iteration":125,"passed_time":8.079831375,"remaining_time":56.04581446},
{"learn":[0.01284125921],"iteration":126,"passed_time":8.139364012,"remaining_time":55.9501164},
{"learn":[0.01283081894],"iteration":127,"passed_time":8.201415122,"remaining_time":55.87214052},
{"learn":[0.01271902221],"iteration":128,"passed_time":8.266279458,"remaining_time":55.81340626},
{"learn":[0.01270402261],"iteration":129,"passed_time":8.321884132,"remaining_time":55.69260919},
{"learn":[0.0126158319],"iteration":130,"passed_time":8.389217371,"remaining_time":55.65060989},
{"learn":[0.0124905611],"iteration":131,"passed_time":8.457901315,"remaining_time":55.61710865},
{"learn":[0.01247234886],"iteration":132,"passed_time":8.512849022,"remaining_time":55.4935346},
{"learn":[0.01246404389],"iteration":133,"passed_time":8.55472765,"remaining_time":55.28652347},
{"learn":[0.01245278198],"iteration":134,"passed_time":8.624791368,"remaining_time":55.2625521},
{"learn":[0.01235318094],"iteration":135,"passed_time":8.678191691,"remaining_time":55.13204133},
{"learn":[0.01233273154],"iteration":136,"passed_time":8.748172087,"remaining_time":55.10709862},
{"learn":[0.01221320442],"iteration":137,"passed_time":8.806265657,"remaining_time":55.00725359},
{"learn":[0.01218235654],"iteration":138,"passed_time":8.867581632,"remaining_time":54.92796967},
{"learn":[0.01216445267],"iteration":139,"passed_time":8.932134177,"remaining_time":54.86882423},
{"learn":[0.01213947057],"iteration":140,"passed_time":8.994180619,"remaining_time":54.79433441},
{"learn":[0.01207819231],"iteration":141,"passed_time":9.057626035,"remaining_time":54.7284728},
{"learn":[0.01206693883],"iteration":142,"passed_time":9.124389796,"remaining_time":54.68253185},
{"learn":[0.01206199739],"iteration":143,"passed_time":9.198329442,"remaining_time":54.67895835},
{"learn":[0.01202892182],"iteration":144,"passed_time":9.277940561,"remaining_time":54.70785641},
{"learn":[0.01199347942],"iteration":145,"passed_time":9.340430024,"remaining_time":54.63511809},
{"learn":[0.01187061578],"iteration":146,"passed_time":9.399066406,"remaining_time":54.54016085},
{"learn":[0.01183853173],"iteration":147,"passed_time":9.464967994,"remaining_time":54.48751845},
{"learn":[0.01180218424],"iteration":148,"passed_time":9.529943167,"remaining_time":54.42940695},
{"learn":[0.01171413062],"iteration":149,"passed_time":9.584999696,"remaining_time":54.31499828},
{"learn":[0.01170328829],"iteration":150,"passed_time":9.644325042,"remaining_time":54.22537722},
{"learn":[0.01160586013],"iteration":151,"passed_time":9.716007353,"remaining_time":54.20509365},
{"learn":[0.01156380484],"iteration":152,"passed_time":9.777105937,"remaining_time":54.12554724},
{"learn":[0.01148340508],"iteration":153,"passed_time":9.835591334,"remaining_time":54.03188486},
{"learn":[0.01143319569],"iteration":154,"passed_time":9.894001844,"remaining_time":53.93826812},
{"learn":[0.01141915516],"iteration":155,"passed_time":9.955524488,"remaining_time":53.86194018},
{"learn":[0.01141347475],"iteration":156,"passed_time":10.01147715,"remaining_time":53.75589321},
{"learn":[0.01140834307],"iteration":157,"passed_time":10.05898881,"remaining_time":53.60549731},
{"learn":[0.01127147998],"iteration":158,"passed_time":10.11227239,"remaining_time":53.48692505},
{"learn":[0.01126335884],"iteration":159,"passed_time":10.16654799,"remaining_time":53.37437697},
{"learn":[0.01116504593],"iteration":160,"passed_time":10.22028357,"remaining_time":53.25973861},
{"learn":[0.0111521687],"iteration":161,"passed_time":10.2628559,"remaining_time":53.08810645},
{"learn":[0.01109782699],"iteration":162,"passed_time":10.32681162,"remaining_time":53.02786088},
{"learn":[0.01105578085],"iteration":163,"passed_time":10.38915007,"remaining_time":52.95932595},
{"learn":[0.01102980763],"iteration":164,"passed_time":10.4691476,"remaining_time":52.9802318},
{"learn":[0.01093745935],"iteration":165,"passed_time":10.52976352,"remaining_time":52.90254684},
{"learn":[0.0108651746],"iteration":166,"passed_time":10.59104758,"remaining_time":52.82839901},
{"learn":[0.01085027715],"iteration":167,"passed_time":10.67668011,"remaining_time":52.8749872},
{"learn":[0.01083106672],"iteration":168,"passed_time":10.73334889,"remaining_time":52.7775913},
{"learn":[0.01081478636],"iteration":169,"passed_time":10.7877679,"remaining_time":52.66969034},
{"learn":[0.01080056623],"iteration":170,"passed_time":10.84321558,"remaining_time":52.56740184},
{"learn":[0.0107437656],"iteration":171,"passed_time":10.90670331,"remaining_time":52.50436243},
{"learn":[0.01072880649],"iteration":172,"passed_time":10.96797082,"remaining_time":52.43070444},
{"learn":[0.01066880324],"iteration":173,"passed_time":11.06401218,"remaining_time":52.5222647},
{"learn":[0.01063628063],"iteration":174,"passed_time":11.10753047,"remaining_time":52.3640722},
{"learn":[0.01061976117],"iteration":175,"passed_time":11.17394901,"remaining_time":52.31439765},
{"learn":[0.01060314229],"iteration":176,"passed_time":11.23704145,"remaining_time":52.24906843},
{"learn":[0.01059781459],"iteration":177,"passed_time":11.28357515,"remaining_time":52.10729648},
{"learn":[0.01059063234],"iteration":178,"passed_time":11.33661844,"remaining_time":51.99644545},
{"learn":[0.01056638154],"iteration":179,"passed_time":11.38899093,"remaining_time":51.88318089},
{"learn":[0.01052144735],"iteration":180,"passed_time":11.44820057,"remaining_time":51.80152635},
{"learn":[0.01051265731],"iteration":181,"passed_time":11.51008702,"remaining_time":51.73214936},
{"learn":[0.01041747103],"iteration":182,"passed_time":11.57666128,"remaining_time":51.68378286},
{"learn":[0.01041025975],"iteration":183,"passed_time":11.63229275,"remaining_time":51.58668956},
{"learn":[0.01034489914],"iteration":184,"passed_time":11.69957686,"remaining_time":51.54137914},
{"learn":[0.01033788394],"iteration":185,"passed_time":11.80414097,"remaining_time":51.65898253},
{"learn":[0.01033583227],"iteration":186,"passed_time":11.86507267,"remaining_time":51.58451379},
{"learn":[0.01028592396],"iteration":187,"passed_time":11.92945992,"remaining_time":51.52511414},
{"learn":[0.01026510958],"iteration":188,"passed_time":11.9961451,"remaining_time":51.4755221},
{"learn":[0.01025541468],"iteration":189,"passed_time":12.05228021,"remaining_time":51.38077353},
{"learn":[0.0102499816],"iteration":190,"passed_time":12.0935983,"remaining_time":51.22367028},
{"learn":[0.01015496936],"iteration":191,"passed_time":12.15868683,"remaining_time":51.16780707},
{"learn":[0.01004556945],"iteration":192,"passed_time":12.22051134,"remaining_time":51.09820026},
{"learn":[0.01003530906],"iteration":193,"passed_time":12.279254,"remaining_time":51.01586972},
{"learn":[0.01002315644],"iteration":194,"passed_time":12.3258554,"remaining_time":50.88365945},
{"learn":[0.01000146469],"iteration":195,"passed_time":12.41032822,"remaining_time":50.9076729},
{"learn":[0.009956215209],"iteration":196,"passed_time":12.46839054,"remaining_time":50.82293201},
{"learn":[0.009944010931],"iteration":197,"passed_time":12.52226922,"remaining_time":50.72151472},
{"learn":[0.009939510311],"iteration":198,"passed_time":12.57045677,"remaining_time":50.59766772},
{"learn":[0.009933837197],"iteration":199,"passed_time":12.63509938,"remaining_time":50.54039753},
{"learn":[0.009886001551],"iteration":200,"passed_time":12.69650989,"remaining_time":50.470206},
{"learn":[0.009880397578],"iteration":201,"passed_time":12.7767346,"remaining_time":50.47442677},
{"learn":[0.009870643621],"iteration":202,"passed_time":12.83765268,"remaining_time":50.4020157},
{"learn":[0.009861759709],"iteration":203,"passed_time":12.8964741,"remaining_time":50.3215362},
{"learn":[0.009829416941],"iteration":204,"passed_time":12.96337738,"remaining_time":50.27260984},
{"learn":[0.009751366773],"iteration":205,"passed_time":13.01410992,"remaining_time":50.16118094},
{"learn":[0.009699335614],"iteration":206,"passed_time":13.06537974,"remaining_time":50.05239677},
{"learn":[0.009675362834],"iteration":207,"passed_time":13.13406268,"remaining_time":50.01046944},
{"learn":[0.0096206442],"iteration":208,"passed_time":13.19392259,"remaining_time":49.93489364},
{"learn":[0.009618277268],"iteration":209,"passed_time":13.2486774,"remaining_time":49.84026258},
{"learn":[0.00961498374],"iteration":210,"passed_time":13.31315872,"remaining_time":49.78238024},
{"learn":[0.009607669335],"iteration":211,"passed_time":13.36752342,"remaining_time":49.68683233},
{"learn":[0.009539160141],"iteration":212,"passed_time":13.43148421,"remaining_time":49.6271271},
{"learn":[0.009481970802],"iteration":213,"passed_time":13.491846,"remaining_time":49.55416336},
{"learn":[0.009431513663],"iteration":214,"passed_time":13.55869394,"remaining_time":49.5049988},
{"learn":[0.009402062877],"iteration":215,"passed_time":13.61730683,"remaining_time":49.42578034},
{"learn":[0.009395900442],"iteration":216,"passed_time":13.66117933,"remaining_time":49.29356412},
{"learn":[0.009363167994],"iteration":217,"passed_time":13.72666739,"remaining_time":49.23969679},
{"learn":[0.0093528134],"iteration":218,"passed_time":13.78899396,"remaining_time":49.17444878},
{"learn":[0.009327567408],"iteration":219,"passed_time":13.85317109,"remaining_time":49.11578842},
{"learn":[0.009268061734],"iteration":220,"passed_time":13.91132585,"remaining_time":49.03584996},
{"learn":[0.009242383127],"iteration":221,"passed_time":13.96952164,"remaining_time":48.95625152},
{"learn":[0.009219436115],"iteration":222,"passed_time":14.06892713,"remaining_time":49.0204322},
{"learn":[0.009213309208],"iteration":223,"passed_time":14.13196735,"remaining_time":48.95717262},
{"learn":[0.009169486875],"iteration":224,"passed_time":14.19669017,"remaining_time":48.89971059},
{"learn":[0.009117583817],"iteration":225,"passed_time":14.26151692,"remaining_time":48.84254026},
{"learn":[0.009085096816],"iteration":226,"passed_time":14.3205814,"remaining_time":48.76568026},
{"learn":[0.00906783643],"iteration":227,"passed_time":14.3842384,"remaining_time":48.70452651},
{"learn":[0.009036315853],"iteration":228,"passed_time":14.4663801,"remaining_time":48.70558541},
{"learn":[0.009018295129],"iteration":229,"passed_time":14.52779323,"remaining_time":48.63652515},
{"learn":[0.009008751849],"iteration":230,"passed_time":14.58068516,"remaining_time":48.53916401},
{"learn":[0.008988839946],"iteration":231,"passed_time":14.64360171,"remaining_time":48.47537119},
{"learn":[0.008926587069],"iteration":232,"passed_time":14.71172696,"remaining_time":48.42873211},
{"learn":[0.008920217738],"iteration":233,"passed_time":14.78143868,"remaining_time":48.38710268},
{"learn":[0.008917853022],"iteration":234,"passed_time":14.84953906,"remaining_time":48.33998885},
{"learn":[0.008880077457],"iteration":235,"passed_time":14.9089274,"remaining_time":48.26449379},
{"learn":[0.008843389376],"iteration":236,"passed_time":14.97679073,"remaining_time":48.21641911},
{"learn":[0.008827823106],"iteration":237,"passed_time":15.04733297,"remaining_time":48.17675512},
{"learn":[0.008801955532],"iteration":238,"passed_time":15.1195915,"remaining_time":48.14229761},
{"learn":[0.008778994989],"iteration":239,"passed_time":15.16359367,"remaining_time":48.01804663},
{"learn":[0.008718059286],"iteration":240,"passed_time":15.22573558,"remaining_time":47.95159049},
{"learn":[0.008707875266],"iteration":241,"passed_time":15.27364675,"remaining_time":47.840596},
{"learn":[0.008706565591],"iteration":242,"passed_time":15.31861719,"remaining_time":47.72095972},
{"learn":[0.008653167235],"iteration":243,"passed_time":15.38269693,"remaining_time":47.66114295},
{"learn":[0.008637537238],"iteration":244,"passed_time":15.44009839,"remaining_time":47.58071136},
{"learn":[0.008629991334],"iteration":245,"passed_time":15.50202937,"remaining_time":47.51435017},
{"learn":[0.008594979025],"iteration":246,"passed_time":15.56645501,"remaining_time":47.45563004},
{"learn":[0.008571728731],"iteration":247,"passed_time":15.63443359,"remaining_time":47.40763732},
{"learn":[0.008556058927],"iteration":248,"passed_time":15.68973613,"remaining_time":47.32125234},
{"learn":[0.008548032882],"iteration":249,"passed_time":15.75697473,"remaining_time":47.2709242},
{"learn":[0.008540471542],"iteration":250,"passed_time":15.80920217,"remaining_time":47.17566705},
{"learn":[0.00850155894],"iteration":251,"passed_time":15.86285039,"remaining_time":47.08496861},
{"learn":[0.00850038724],"iteration":252,"passed_time":15.89600045,"remaining_time":46.93404086},
{"learn":[0.008440278173],"iteration":253,"passed_time":15.95991369,"remaining_time":46.87439218},
{"learn":[0.008382018137],"iteration":254,"passed_time":16.01646412,"remaining_time":46.7931991},
{"learn":[0.008316628023],"iteration":255,"passed_time":16.08015922,"remaining_time":46.73296274},
{"learn":[0.008259757888],"iteration":256,"passed_time":16.1391406,"remaining_time":46.65907185},
{"learn":[0.008220879088],"iteration":257,"passed_time":16.20440635,"remaining_time":46.60337019},
{"learn":[0.008175741818],"iteration":258,"passed_time":16.2573759,"remaining_time":46.51241522},
{"learn":[0.00812141096],"iteration":259,"passed_time":16.31278717,"remaining_time":46.42870194},
{"learn":[0.008083666395],"iteration":260,"passed_time":16.38251047,"remaining_time":46.38572888},
{"learn":[0.008039753162],"iteration":261,"passed_time":16.42863984,"remaining_time":46.27609237},
{"learn":[0.008037077076],"iteration":262,"passed_time":16.48380979,"remaining_time":46.19227305},
{"learn":[0.0079926865],"iteration":263,"passed_time":16.54637523,"remaining_time":46.12928853},
{"learn":[0.007983187841],"iteration":264,"passed_time":16.6081527,"remaining_time":46.06412163},
{"learn":[0.007979272845],"iteration":265,"passed_time":16.6706133,"remaining_time":46.00086527},
{"learn":[0.007975050748],"iteration":266,"passed_time":16.71707985,"remaining_time":45.89370609},
{"learn":[0.007971903217],"iteration":267,"passed_time":16.79181436,"remaining_time":45.86420937},
{"learn":[0.007927874819],"iteration":268,"passed_time":16.85813366,"remaining_time":45.81150819},
{"learn":[0.007897385717],"iteration":269,"passed_time":16.90801317,"remaining_time":45.71425784},
{"learn":[0.007833272086],"iteration":270,"passed_time":16.97145264,"remaining_time":45.65383386},
{"learn":[0.007827088061],"iteration":271,"passed_time":17.02083043,"remaining_time":45.55575204},
{"learn":[0.00778194531],"iteration":272,"passed_time":17.07300878,"remaining_time":45.46548492},
{"learn":[0.007759064294],"iteration":273,"passed_time":17.1451643,"remaining_time":45.42842803},
{"learn":[0.00775537237],"iteration":274,"passed_time":17.18820723,"remaining_time":45.31436451},
{"learn":[0.007707667947],"iteration":275,"passed_time":17.24142616,"remaining_time":45.2275092},
{"learn":[0.007689345066],"iteration":276,"passed_time":17.29239909,"remaining_time":45.13503445},
{"learn":[0.007686303083],"iteration":277,"passed_time":17.33582649,"remaining_time":45.0232616},
{"learn":[0.007654988178],"iteration":278,"passed_time":17.40331118,"remaining_time":44.97414825},
{"learn":[0.007628412646],"iteration":279,"passed_time":17.45489493,"remaining_time":44.88401553},
{"learn":[0.007566258991],"iteration":280,"passed_time":17.50681681,"remaining_time":44.79502236},
{"learn":[0.007521956293],"iteration":281,"passed_time":17.57287385,"remaining_time":44.74228164},
{"learn":[0.007481645064],"iteration":282,"passed_time":17.63609162,"remaining_time":44.68225332},
{"learn":[0.007477833853],"iteration":283,"passed_time":17.70245573,"remaining_time":44.63013487},
{"learn":[0.007442698047],"iteration":284,"passed_time":17.75915196,"remaining_time":44.55366195},
{"learn":[0.007437521655],"iteration":285,"passed_time":17.82376058,"remaining_time":44.4970806},
{"learn":[0.007414827843],"iteration":286,"passed_time":17.89159048,"remaining_time":44.44844604},
{"learn":[0.007414820117],"iteration":287,"passed_time":17.93195732,"remaining_time":44.33178337},
{"learn":[0.007413070835],"iteration":288,"passed_time":17.97931548,"remaining_time":44.23284881},
{"learn":[0.007399482719],"iteration":289,"passed_time":18.03447257,"remaining_time":44.15336389},
{"learn":[0.007398492014],"iteration":290,"passed_time":18.10113228,"remaining_time":44.10207142},
{"learn":[0.007345064786],"iteration":291,"passed_time":18.15516745,"remaining_time":44.02006354},
{"learn":[0.007345060055],"iteration":292,"passed_time":18.20950625,"remaining_time":43.93897925},
{"learn":[0.007311268601],"iteration":293,"passed_time":18.2885272,"remaining_time":43.91734763},
{"learn":[0.007304385954],"iteration":294,"passed_time":18.35277865,"remaining_time":43.86003033},
{"learn":[0.007279109016],"iteration":295,"passed_time":18.411958,"remaining_time":43.79060281},
{"learn":[0.007237982633],"iteration":296,"passed_time":18.45959905,"remaining_time":43.69393311},
{"learn":[0.00723702189],"iteration":297,"passed_time":18.51532406,"remaining_time":43.61663586},
{"learn":[0.00720656327],"iteration":298,"passed_time":18.57551499,"remaining_time":43.54995319},
{"learn":[0.00717313573],"iteration":299,"passed_time":18.63604024,"remaining_time":43.48409389},
{"learn":[0.007139593456],"iteration":300,"passed_time":18.6915516,"remaining_time":43.40662647},
{"learn":[0.007096647362],"iteration":301,"passed_time":18.77273221,"remaining_time":43.38863272},
{"learn":[0.007080030952],"iteration":302,"passed_time":18.83746904,"remaining_time":43.33239578},
{"learn":[0.00702749962],"iteration":303,"passed_time":18.89907481,"remaining_time":43.26893443},
{"learn":[0.006965621916],"iteration":304,"passed_time":18.9582597,"remaining_time":43.19996883},
{"learn":[0.006919412641],"iteration":305,"passed_time":19.02111678,"remaining_time":43.13939558},
{"learn":[0.00687759583],"iteration":306,"passed_time":19.07883105,"remaining_time":43.06719843},
{"learn":[0.006858765669],"iteration":307,"passed_time":19.1444912,"remaining_time":43.01294777},
{"learn":[0.006840382782],"iteration":308,"passed_time":19.20519647,"remaining_time":42.9475429},
{"learn":[0.006824497007],"iteration":309,"passed_time":19.26954105,"remaining_time":42.89026879},
{"learn":[0.00681917709],"iteration":310,"passed_time":19.31972828,"remaining_time":42.80158453},
{"learn":[0.006799769107],"iteration":311,"passed_time":19.39282035,"remaining_time":42.76365514},
{"learn":[0.006797349057],"iteration":312,"passed_time":19.45221595,"remaining_time":42.69543885},
{"learn":[0.006780646559],"iteration":313,"passed_time":19.5054555,"remaining_time":42.61382952},
{"learn":[0.006777544884],"iteration":314,"passed_time":19.55512107,"remaining_time":42.52462835},
{"learn":[0.006775116444],"iteration":315,"passed_time":19.62042578,"remaining_time":42.46952922},
{"learn":[0.006765125169],"iteration":316,"passed_time":19.69059929,"remaining_time":42.42485588},
{"learn":[0.006746624232],"iteration":317,"passed_time":19.7477106,"remaining_time":42.35200826},
{"learn":[0.006730890827],"iteration":318,"passed_time":19.81536385,"remaining_time":42.3017642},
{"learn":[0.006724008859],"iteration":319,"passed_time":19.87738985,"remaining_time":42.23945343},
{"learn":[0.006724003452],"iteration":320,"passed_time":19.9279682,"remaining_time":42.15292961},
{"learn":[0.006720601038],"iteration":321,"passed_time":19.99677882,"remaining_time":42.10501876},
{"learn":[0.006720581895],"iteration":322,"passed_time":20.05537263,"remaining_time":42.0355643},
{"learn":[0.006694794268],"iteration":323,"passed_time":20.11135847,"remaining_time":41.96073557},
{"learn":[0.006640029769],"iteration":324,"passed_time":20.17206733,"remaining_time":41.89583214},
{"learn":[0.006630988226],"iteration":325,"passed_time":20.23189129,"remaining_time":41.82912494},
{"learn":[0.006619899192],"iteration":326,"passed_time":20.29667714,"remaining_time":41.77267191},
{"learn":[0.00659350812],"iteration":327,"passed_time":20.35965902,"remaining_time":41.71247214},
{"learn":[0.006558489973],"iteration":328,"passed_time":20.42337525,"remaining_time":41.65375318},
{"learn":[0.006552558323],"iteration":329,"passed_time":20.4848232,"remaining_time":41.59039861},
{"learn":[0.006552552358],"iteration":330,"passed_time":20.53193997,"remaining_time":41.49809016},
{"learn":[0.00655136509],"iteration":331,"passed_time":20.58699402,"remaining_time":41.42202412},
{"learn":[0.006513258299],"iteration":332,"passed_time":20.64819002,"remaining_time":41.35838662},
{"learn":[0.006487043612],"iteration":333,"passed_time":20.70950186,"remaining_time":41.29499473},
{"learn":[0.00648703685],"iteration":334,"passed_time":20.77094978,"remaining_time":41.23188538},
{"learn":[0.006462447725],"iteration":335,"passed_time":20.82672761,"remaining_time":41.15758076},
{"learn":[0.006422984188],"iteration":336,"passed_time":20.88303578,"remaining_time":41.08442944},
{"learn":[0.006422972835],"iteration":337,"passed_time":20.92366385,"remaining_time":40.98066707},
{"learn":[0.006411306359],"iteration":338,"passed_time":21.03245914,"remaining_time":41.01019318},
{"learn":[0.006375757943],"iteration":339,"passed_time":21.105931,"remaining_time":40.97033664},
{"learn":[0.006355565886],"iteration":340,"passed_time":21.18673492,"remaining_time":40.94445252},
{"learn":[0.006311972291],"iteration":341,"passed_time":21.24811208,"remaining_time":40.88087061},
{"learn":[0.006278638737],"iteration":342,"passed_time":21.32082162,"remaining_time":40.83900817},
{"learn":[0.006264975074],"iteration":343,"passed_time":21.40649896,"remaining_time":40.82169568},
{"learn":[0.006232718456],"iteration":344,"passed_time":21.45000295,"remaining_time":40.72391865},
{"learn":[0.00620633965],"iteration":345,"passed_time":21.52538634,"remaining_time":40.6867129},
{"learn":[0.00618825719],"iteration":346,"passed_time":21.5886136,"remaining_time":40.62641119},
{"learn":[0.006157429205],"iteration":347,"passed_time":21.65378639,"remaining_time":40.56973771},
{"learn":[0.00614556383],"iteration":348,"passed_time":21.73777533,"remaining_time":40.54811388},
{"learn":[0.006100583798],"iteration":349,"passed_time":21.79388839,"remaining_time":40.47436415},
{"learn":[0.006100580817],"iteration":350,"passed_time":21.86031739,"remaining_time":40.41978914},
{"learn":[0.006076491666],"iteration":351,"passed_time":21.91953599,"remaining_time":40.35187307},
{"learn":[0.006045726322],"iteration":352,"passed_time":21.97505637,"remaining_time":40.27722796},
{"learn":[0.006043100938],"iteration":353,"passed_time":22.06163558,"remaining_time":40.25936888},
{"learn":[0.006042278998],"iteration":354,"passed_time":22.1227802,"remaining_time":40.1949105},
{"learn":[0.006041226436],"iteration":355,"passed_time":22.19208904,"remaining_time":40.14523972},
{"learn":[0.006033334574],"iteration":356,"passed_time":22.2981321,"remaining_time":40.16162168},
{"learn":[0.006027587237],"iteration":357,"passed_time":22.38425936,"remaining_time":40.14160477},
{"learn":[0.006009373641],"iteration":358,"passed_time":22.45203274,"remaining_time":40.08844843},
{"learn":[0.005985780286],"iteration":359,"passed_time":22.53902565,"remaining_time":40.06937892},
{"learn":[0.005971371411],"iteration":360,"passed_time":22.62913196,"remaining_time":40.05544411},
{"learn":[0.005950277993],"iteration":361,"passed_time":22.69360459,"remaining_time":39.99591084},
{"learn":[0.005923025041],"iteration":362,"passed_time":22.75903465,"remaining_time":39.93803049},
{"learn":[0.005915157132],"iteration":363,"passed_time":22.84813015,"remaining_time":39.92145817},
{"learn":[0.005915140228],"iteration":364,"passed_time":22.90310902,"remaining_time":39.84513486},
{"learn":[0.00591511415],"iteration":365,"passed_time":22.9732619,"remaining_time":39.79521323},
{"learn":[0.005902143861],"iteration":366,"passed_time":23.09162494,"remaining_time":39.82833402},
{"learn":[0.005891415243],"iteration":367,"passed_time":23.1710156,"remaining_time":39.79370071},
{"learn":[0.005880757463],"iteration":368,"passed_time":23.23014209,"remaining_time":39.72417251},
{"learn":[0.005860144086],"iteration":369,"passed_time":23.27967402,"remaining_time":39.63836387},
{"learn":[0.005860143505],"iteration":370,"passed_time":23.33481951,"remaining_time":39.56226812},
{"learn":[0.005835904188],"iteration":371,"passed_time":23.38928407,"remaining_time":39.48513548},
{"learn":[0.005807565407],"iteration":372,"passed_time":23.45080037,"remaining_time":39.4199781},
{"learn":[0.005800765075],"iteration":373,"passed_time":23.50732756,"remaining_time":39.34648945},
{"learn":[0.005787857858],"iteration":374,"passed_time":23.5875516,"remaining_time":39.312586},
{"learn":[0.00577921531],"iteration":375,"passed_time":23.6987411,"remaining_time":39.32982565},
{"learn":[0.005769772386],"iteration":376,"passed_time":23.75435438,"remaining_time":39.25454319},
{"learn":[0.005752812305],"iteration":377,"passed_time":23.83325264,"remaining_time":39.21768026},
{"learn":[0.005746206616],"iteration":378,"passed_time":23.89086845,"remaining_time":39.14572376},
{"learn":[0.005714674526],"iteration":379,"passed_time":23.95771069,"remaining_time":39.08889638},
{"learn":[0.005699098439],"iteration":380,"passed_time":24.02551186,"remaining_time":39.03357439},
{"learn":[0.005685940388],"iteration":381,"passed_time":24.12586385,"remaining_time":39.03084781},
{"learn":[0.005672750126],"iteration":382,"passed_time":24.20021243,"remaining_time":38.98572082},
{"learn":[0.005665578928],"iteration":383,"passed_time":24.26470611,"remaining_time":38.92463273},
{"learn":[0.005651082416],"iteration":384,"passed_time":24.33336251,"remaining_time":38.87017647},
{"learn":[0.005651081493],"iteration":385,"passed_time":24.39382395,"remaining_time":38.80261116},
{"learn":[0.005649753489],"iteration":386,"passed_time":24.47133941,"remaining_time":38.76209576},
{"learn":[0.005640707907],"iteration":387,"passed_time":24.5355663,"remaining_time":38.70042932},
{"learn":[0.005623052399],"iteration":388,"passed_time":24.59528189,"remaining_time":38.63166385},
{"learn":[0.005623050509],"iteration":389,"passed_time":24.65497795,"remaining_time":38.56291423},
{"learn":[0.00561768777],"iteration":390,"passed_time":24.71922884,"remaining_time":38.50130528},
{"learn":[0.005615161162],"iteration":391,"passed_time":24.76813803,"remaining_time":38.41588756},
{"learn":[0.005593749128],"iteration":392,"passed_time":24.86016128,"remaining_time":38.39724656},
{"learn":[0.005577358084],"iteration":393,"passed_time":24.91692472,"remaining_time":38.32400097},
{"learn":[0.005577356419],"iteration":394,"passed_time":24.98051591,"remaining_time":38.26129652},
{"learn":[0.005565512059],"iteration":395,"passed_time":25.03977578,"remaining_time":38.19198125},
{"learn":[0.005556306792],"iteration":396,"passed_time":25.10052237,"remaining_time":38.12497478},
{"learn":[0.005538972045],"iteration":397,"passed_time":25.18260523,"remaining_time":38.09027224},
{"learn":[0.0055275902],"iteration":398,"passed_time":25.25523753,"remaining_time":38.04109713},
{"learn":[0.005523290122],"iteration":399,"passed_time":25.30241556,"remaining_time":37.95362334},
{"learn":[0.005511269884],"iteration":400,"passed_time":25.35998418,"remaining_time":37.88187164},
{"learn":[0.00549668071],"iteration":401,"passed_time":25.44589958,"remaining_time":37.85235808},
{"learn":[0.005486904833],"iteration":402,"passed_time":25.52285834,"remaining_time":37.80929635},
{"learn":[0.005473753354],"iteration":403,"passed_time":25.59635811,"remaining_time":37.76096395},
{"learn":[0.005460370516],"iteration":404,"passed_time":25.67709387,"remaining_time":37.72313791},
{"learn":[0.005439798016],"iteration":405,"passed_time":25.73437503,"remaining_time":37.65078514},
{"learn":[0.005434831968],"iteration":406,"passed_time":25.80063794,"remaining_time":37.59159287},
{"learn":[0.005422228889],"iteration":407,"passed_time":25.86100447,"remaining_time":37.5238104},
{"learn":[0.005418112676],"iteration":408,"passed_time":25.93092112,"remaining_time":37.46986401},
{"learn":[0.005385885121],"iteration":409,"passed_time":26.00418802,"remaining_time":37.42066081},
{"learn":[0.005370202306],"iteration":410,"passed_time":26.06054858,"remaining_time":37.3471122},
{"learn":[0.005359589647],"iteration":411,"passed_time":26.13919885,"remaining_time":37.30545855},
{"learn":[0.00535879858],"iteration":412,"passed_time":26.19049163,"remaining_time":37.22474234},
{"learn":[0.00534012078],"iteration":413,"passed_time":26.24539618,"remaining_time":37.14928058},
{"learn":[0.005322376032],"iteration":414,"passed_time":26.3076674,"remaining_time":37.08430224},
{"learn":[0.005315042229],"iteration":415,"passed_time":26.3573507,"remaining_time":37.00166541},
{"learn":[0.005300025721],"iteration":416,"passed_time":26.41147948,"remaining_time":36.92540177},
{"learn":[0.005294699793],"iteration":417,"passed_time":26.4900412,"remaining_time":36.88326311},
{"learn":[0.005268095031],"iteration":418,"passed_time":26.5726876,"remaining_time":36.84661454},
{"learn":[0.005253356525],"iteration":419,"passed_time":26.64570477,"remaining_time":36.79644944},
{"learn":[0.005241385212],"iteration":420,"passed_time":26.71459814,"remaining_time":36.74050433},
{"learn":[0.005216467843],"iteration":421,"passed_time":26.79522763,"remaining_time":36.70057245},
{"learn":[0.005204036599],"iteration":422,"passed_time":26.87972033,"remaining_time":36.6657178},
{"learn":[0.005191294795],"iteration":423,"passed_time":26.93929457,"remaining_time":36.59677753},
{"learn":[0.005176659537],"iteration":424,"passed_time":27.01188337,"remaining_time":36.54548927},
{"learn":[0.00516284894],"iteration":425,"passed_time":27.0959875,"remaining_time":36.50961696},
{"learn":[0.00515908996],"iteration":426,"passed_time":27.15885161,"remaining_time":36.44501633},
{"learn":[0.005136056036],"iteration":427,"passed_time":27.22604514,"remaining_time":36.38620986},
{"learn":[0.005119414031],"iteration":428,"passed_time":27.28118136,"remaining_time":36.31131598},
{"learn":[0.00510498743],"iteration":429,"passed_time":27.34897245,"remaining_time":36.25328906},
{"learn":[0.005089193924],"iteration":430,"passed_time":27.41063666,"remaining_time":36.18712822},
{"learn":[0.005079346673],"iteration":431,"passed_time":27.46959065,"remaining_time":36.11742474},
{"learn":[0.005070580609],"iteration":432,"passed_time":27.52811658,"remaining_time":36.0472104},
{"learn":[0.005067433014],"iteration":433,"passed_time":27.60676459,"remaining_time":36.00329207},
{"learn":[0.005044349392],"iteration":434,"passed_time":27.70209787,"remaining_time":35.98088574},
{"learn":[0.005041463091],"iteration":435,"passed_time":27.80445224,"remaining_time":35.9672272},
{"learn":[0.005030479487],"iteration":436,"passed_time":27.88557278,"remaining_time":35.92580659},
{"learn":[0.00501901384],"iteration":437,"passed_time":27.98455562,"remaining_time":35.90712388},
{"learn":[0.005005854286],"iteration":438,"passed_time":28.05052609,"remaining_time":35.8458887},
{"learn":[0.004992937524],"iteration":439,"passed_time":28.11016977,"remaining_time":35.77657971},
{"learn":[0.004983233295],"iteration":440,"passed_time":28.16362996,"remaining_time":35.69947653},
{"learn":[0.004973011413],"iteration":441,"passed_time":28.20579098,"remaining_time":35.60821577},
{"learn":[0.004964946538],"iteration":442,"passed_time":28.30676665,"remaining_time":35.59112646},
{"learn":[0.004952120102],"iteration":443,"passed_time":28.36520234,"remaining_time":35.52038852},
{"learn":[0.004943059746],"iteration":444,"passed_time":28.44393876,"remaining_time":35.47502475},
{"learn":[0.00493443685],"iteration":445,"passed_time":28.49637159,"remaining_time":35.39683826},
{"learn":[0.004914495174],"iteration":446,"passed_time":28.56582542,"remaining_time":35.33982429},
{"learn":[0.004905344099],"iteration":447,"passed_time":28.61705164,"remaining_time":35.26029577},
{"learn":[0.004897908274],"iteration":448,"passed_time":28.65559748,"remaining_time":35.16533232},
{"learn":[0.004882599153],"iteration":449,"passed_time":28.72205274,"remaining_time":35.10473112},
{"learn":[0.004864713268],"iteration":450,"passed_time":28.78746325,"remaining_time":35.0428322},
{"learn":[0.004838898818],"iteration":451,"passed_time":28.87115445,"remaining_time":35.00308106},
{"learn":[0.004830695061],"iteration":452,"passed_time":28.9418216,"remaining_time":34.9474093},
{"learn":[0.004830687895],"iteration":453,"passed_time":28.99369282,"remaining_time":34.8690667},
{"learn":[0.004817799348],"iteration":454,"passed_time":29.05816478,"remaining_time":34.80593363},
{"learn":[0.004817786202],"iteration":455,"passed_time":29.11445894,"remaining_time":34.73303874},
{"learn":[0.0048177846],"iteration":456,"passed_time":29.16799769,"remaining_time":34.65694255},
{"learn":[0.004796783557],"iteration":457,"passed_time":29.27751768,"remaining_time":34.64719341},
{"learn":[0.004790456058],"iteration":458,"passed_time":29.36024024,"remaining_time":34.60542477},
{"learn":[0.004780789981],"iteration":459,"passed_time":29.4177787,"remaining_time":34.53391413},
{"learn":[0.004776225832],"iteration":460,"passed_time":29.47746599,"remaining_time":34.46497651},
{"learn":[0.004752387258],"iteration":461,"passed_time":29.54193198,"remaining_time":34.40164373},
{"learn":[0.00474920699],"iteration":462,"passed_time":29.63059516,"remaining_time":34.36637063},
{"learn":[0.004723602509],"iteration":463,"passed_time":29.70648009,"remaining_time":34.31610631},
{"learn":[0.004711823662],"iteration":464,"passed_time":29.7851769,"remaining_time":34.26896697},
{"learn":[0.004688967495],"iteration":465,"passed_time":29.86403233,"remaining_time":34.22187396},
{"learn":[0.004686804624],"iteration":466,"passed_time":29.93166844,"remaining_time":34.16184},
{"learn":[0.00468410479],"iteration":467,"passed_time":30.02532719,"remaining_time":34.13135484},
{"learn":[0.004672965235],"iteration":468,"passed_time":30.0957614,"remaining_time":34.07430555},
{"learn":[0.004668615605],"iteration":469,"passed_time":30.15729806,"remaining_time":34.0071659},
{"learn":[0.004657396073],"iteration":470,"passed_time":30.22223968,"remaining_time":33.94387429},
{"learn":[0.004640476051],"iteration":471,"passed_time":30.2835912,"remaining_time":33.87655964},
{"learn":[0.004638493022],"iteration":472,"passed_time":30.35719668,"remaining_time":33.82292315},
{"learn":[0.004636732033],"iteration":473,"passed_time":30.42525616,"remaining_time":33.76304798},
{"learn":[0.004622204744],"iteration":474,"passed_time":30.4814955,"remaining_time":33.69007397},
{"learn":[0.004611854497],"iteration":475,"passed_time":30.56054197,"remaining_time":33.64227729},
{"learn":[0.004607942686],"iteration":476,"passed_time":30.62749282,"remaining_time":33.58108751},
{"learn":[0.004603769663],"iteration":477,"passed_time":30.68328419,"remaining_time":33.50768692},
{"learn":[0.004599830778],"iteration":478,"passed_time":30.76002511,"remaining_time":33.45714631},
{"learn":[0.004589155303],"iteration":479,"passed_time":30.81712983,"remaining_time":33.38522399},
{"learn":[0.004581842907],"iteration":480,"passed_time":30.88737553,"remaining_time":33.32754241},
{"learn":[0.00457205534],"iteration":481,"passed_time":30.95300323,"remaining_time":33.2648458},
{"learn":[0.004572053419],"iteration":482,"passed_time":31.01040796,"remaining_time":33.19333523},
{"learn":[0.004572039826],"iteration":483,"passed_time":31.07100679,"remaining_time":33.12528823},
{"learn":[0.004572033037],"iteration":484,"passed_time":31.1347184,"remaining_time":33.06057727},
{"learn":[0.004567215054],"iteration":485,"passed_time":31.19654205,"remaining_time":32.99387369},
{"learn":[0.004565630837],"iteration":486,"passed_time":31.29776971,"remaining_time":32.96869787},
{"learn":[0.004557912552],"iteration":487,"passed_time":31.35892978,"remaining_time":32.90117223},
{"learn":[0.004557912552],"iteration":488,"passed_time":31.40565538,"remaining_time":32.81858875},
{"learn":[0.004553407117],"iteration":489,"passed_time":31.45009589,"remaining_time":32.73377328},
{"learn":[0.004553393296],"iteration":490,"passed_time":31.4936788,"remaining_time":32.64823322},
{"learn":[0.004553379491],"iteration":491,"passed_time":31.55484259,"remaining_time":32.58101634},
{"learn":[0.004553278553],"iteration":492,"passed_time":31.61346413,"remaining_time":32.51120956},
{"learn":[0.004553275104],"iteration":493,"passed_time":31.66169561,"remaining_time":32.43080563},
{"learn":[0.004553271657],"iteration":494,"passed_time":31.69703095,"remaining_time":32.33737501},
{"learn":[0.004553268206],"iteration":495,"passed_time":31.75571974,"remaining_time":32.26790877},
{"learn":[0.004528414751],"iteration":496,"passed_time":31.81302573,"remaining_time":32.1970864},
{"learn":[0.004524154407],"iteration":497,"passed_time":31.84907061,"remaining_time":32.10488644},
{"learn":[0.004524127913],"iteration":498,"passed_time":31.88525121,"remaining_time":32.01304781},
{"learn":[0.004518272725],"iteration":499,"passed_time":31.95100464,"remaining_time":31.95100464},
{"learn":[0.004518272725],"iteration":500,"passed_time":32.00505793,"remaining_time":31.87729323},
{"learn":[0.004514284776],"iteration":501,"passed_time":32.05460283,"remaining_time":31.79918767},
{"learn":[0.004511440123],"iteration":502,"passed_time":32.10559861,"remaining_time":31.72262924},
{"learn":[0.004511436443],"iteration":503,"passed_time":32.15615054,"remaining_time":31.64573546},
{"learn":[0.004511432759],"iteration":504,"passed_time":32.23520588,"remaining_time":31.59688497},
{"learn":[0.004511419397],"iteration":505,"passed_time":32.30210707,"remaining_time":31.5360492},
{"learn":[0.004511415703],"iteration":506,"passed_time":32.39933456,"remaining_time":31.50467838},
{"learn":[0.004511410389],"iteration":507,"passed_time":32.44853618,"remaining_time":31.42653504},
{"learn":[0.004511410389],"iteration":508,"passed_time":32.50581859,"remaining_time":31.35630044},
{"learn":[0.004507420722],"iteration":509,"passed_time":32.56864411,"remaining_time":31.29144238},
{"learn":[0.00449985648],"iteration":510,"passed_time":32.63329326,"remaining_time":31.22833739},
{"learn":[0.004485805481],"iteration":511,"passed_time":32.6910354,"remaining_time":31.15864312},
{"learn":[0.004472330736],"iteration":512,"passed_time":32.7562676,"remaining_time":31.09610589},
{"learn":[0.004462956943],"iteration":513,"passed_time":32.81436971,"remaining_time":31.0268165},
{"learn":[0.00445597581],"iteration":514,"passed_time":32.89080943,"remaining_time":30.97483995},
{"learn":[0.004443523596],"iteration":515,"passed_time":32.94661397,"remaining_time":30.90341311},
{"learn":[0.004443520271],"iteration":516,"passed_time":32.99572318,"remaining_time":30.82579167},
{"learn":[0.004443518414],"iteration":517,"passed_time":33.06019319,"remaining_time":30.76257358},
{"learn":[0.004443491837],"iteration":518,"passed_time":33.11367997,"remaining_time":30.68917161},
{"learn":[0.004434367162],"iteration":519,"passed_time":33.17003457,"remaining_time":30.61849344},
{"learn":[0.00442781727],"iteration":520,"passed_time":33.21919405,"remaining_time":30.54125518},
{"learn":[0.004427811009],"iteration":521,"passed_time":33.27493654,"remaining_time":30.47015262},
{"learn":[0.004427805476],"iteration":522,"passed_time":33.34957477,"remaining_time":30.41634257},
{"learn":[0.004427792947],"iteration":523,"passed_time":33.41031533,"remaining_time":30.34982843},
{"learn":[0.004427787457],"iteration":524,"passed_time":33.48565066,"remaining_time":30.29654107},
{"learn":[0.004427738129],"iteration":525,"passed_time":33.56936619,"remaining_time":30.25072162},
{"learn":[0.004427730841],"iteration":526,"passed_time":33.626604,"remaining_time":30.18099372},
{"learn":[0.004427681731],"iteration":527,"passed_time":33.68644578,"remaining_time":30.11364092},
{"learn":[0.004427678796],"iteration":528,"passed_time":33.78708478,"remaining_time":30.0826407},
{"learn":[0.00442760579],"iteration":529,"passed_time":33.82025958,"remaining_time":29.99155095},
{"learn":[0.00442760579],"iteration":530,"passed_time":33.85536837,"remaining_time":29.90238751},
{"learn":[0.00442760579],"iteration":531,"passed_time":33.91438801,"remaining_time":29.83446163},
{"learn":[0.004425708619],"iteration":532,"passed_time":33.98941711,"remaining_time":29.78059623},
{"learn":[0.004425679409],"iteration":533,"passed_time":34.04840578,"remaining_time":29.71265373},
{"learn":[0.004422169972],"iteration":534,"passed_time":34.1131368,"remaining_time":29.64973572},
{"learn":[0.004413003125],"iteration":535,"passed_time":34.17762077,"remaining_time":29.58659709},
{"learn":[0.004412991613],"iteration":536,"passed_time":34.23400234,"remaining_time":29.51646757},
{"learn":[0.004409744792],"iteration":537,"passed_time":34.29699338,"remaining_time":29.45206495},
{"learn":[0.004409715956],"iteration":538,"passed_time":34.35629894,"remaining_time":29.38451542},
{"learn":[0.004409669927],"iteration":539,"passed_time":34.42413293,"remaining_time":29.32426138},
{"learn":[0.004409601417],"iteration":540,"passed_time":34.47393241,"remaining_time":29.24867833},
{"learn":[0.004409600695],"iteration":541,"passed_time":34.50667901,"remaining_time":29.15878042},
{"learn":[0.004409600254],"iteration":542,"passed_time":34.58450194,"remaining_time":29.10703018},
{"learn":[0.004409588672],"iteration":543,"passed_time":34.66092434,"remaining_time":29.05401011},
{"learn":[0.004409582895],"iteration":544,"passed_time":34.70712117,"remaining_time":28.97566996},
{"learn":[0.004407643906],"iteration":545,"passed_time":34.75916181,"remaining_time":28.9023067},
{"learn":[0.004407631728],"iteration":546,"passed_time":34.80141407,"remaining_time":28.82091513},
{"learn":[0.00440762997],"iteration":547,"passed_time":34.8574951,"remaining_time":28.7510726},
{"learn":[0.004407628212],"iteration":548,"passed_time":34.89395661,"remaining_time":28.6651629},
{"learn":[0.004407626455],"iteration":549,"passed_time":34.95219692,"remaining_time":28.59725202},
{"learn":[0.004407624699],"iteration":550,"passed_time":35.01253206,"remaining_time":28.5310833},
{"learn":[0.004407623974],"iteration":551,"passed_time":35.04791299,"remaining_time":28.44468301},
{"learn":[0.004407620462],"iteration":552,"passed_time":35.11264537,"remaining_time":28.38219255},
{"learn":[0.004407619738],"iteration":553,"passed_time":35.16607271,"remaining_time":28.31059283},
{"learn":[0.004407616228],"iteration":554,"passed_time":35.21951009,"remaining_time":28.23906665},
{"learn":[0.004407599847],"iteration":555,"passed_time":35.25473463,"remaining_time":28.15306147},
{"learn":[0.004407599123],"iteration":556,"passed_time":35.31064392,"remaining_time":28.08368987},
{"learn":[0.004407595616],"iteration":557,"passed_time":35.38015979,"remaining_time":28.02514449},
{"learn":[0.004407579246],"iteration":558,"passed_time":35.41472691,"remaining_time":27.9389885},
{"learn":[0.004407575741],"iteration":559,"passed_time":35.47172574,"remaining_time":27.87064165},
{"learn":[0.004407575741],"iteration":560,"passed_time":35.52705506,"remaining_time":27.80102882},
{"learn":[0.004407575016],"iteration":561,"passed_time":35.57135947,"remaining_time":27.72287447},
{"learn":[0.004407571513],"iteration":562,"passed_time":35.64409773,"remaining_time":27.66691067},
{"learn":[0.004407568013],"iteration":563,"passed_time":35.70746791,"remaining_time":27.60364541},
{"learn":[0.004407556429],"iteration":564,"passed_time":35.76811545,"remaining_time":27.53828358},
{"learn":[0.004407555555],"iteration":565,"passed_time":35.8281656,"remaining_time":27.47248034},
{"learn":[0.004407554681],"iteration":566,"passed_time":35.88990765,"remaining_time":27.40798944},
{"learn":[0.004407486571],"iteration":567,"passed_time":35.93784595,"remaining_time":27.3330096},
{"learn":[0.004407479595],"iteration":568,"passed_time":36.01493717,"remaining_time":27.28020724},
{"learn":[0.00440747611],"iteration":569,"passed_time":36.08990356,"remaining_time":27.22571672},
{"learn":[0.004406311973],"iteration":570,"passed_time":36.14579972,"remaining_time":27.15682676},
{"learn":[0.004406308509],"iteration":571,"passed_time":36.17883813,"remaining_time":27.07087888},
{"learn":[0.004406307079],"iteration":572,"passed_time":36.22075977,"remaining_time":26.99173547},
{"learn":[0.004406303617],"iteration":573,"passed_time":36.25952254,"remaining_time":26.91037735},
{"learn":[0.004406295222],"iteration":574,"passed_time":36.32887381,"remaining_time":26.85177629},
{"learn":[0.00440628683],"iteration":575,"passed_time":36.3858671,"remaining_time":26.78404106},
{"learn":[0.00440628337],"iteration":576,"passed_time":36.44706408,"remaining_time":26.7194248},
{"learn":[0.004406277651],"iteration":577,"passed_time":36.49844056,"remaining_time":26.64765037},
{"learn":[0.004406270739],"iteration":578,"passed_time":36.56135941,"remaining_time":26.58433905},
{"learn":[0.004406269012],"iteration":579,"passed_time":36.60945035,"remaining_time":26.51029163},
{"learn":[0.004406267286],"iteration":580,"passed_time":36.65056333,"remaining_time":26.43130126},
{"learn":[0.004406265189],"iteration":581,"passed_time":36.68736464,"remaining_time":26.34934437},
{"learn":[0.004406242339],"iteration":582,"passed_time":36.72502825,"remaining_time":26.26815915},
{"learn":[0.004405463742],"iteration":583,"passed_time":36.77720793,"remaining_time":26.19746318},
{"learn":[0.004405450175],"iteration":584,"passed_time":36.82918079,"remaining_time":26.12668381},
{"learn":[0.004405444812],"iteration":585,"passed_time":36.87379513,"remaining_time":26.05076994},
{"learn":[0.004405439446],"iteration":586,"passed_time":36.93184561,"remaining_time":25.98441607},
{"learn":[0.004405437759],"iteration":587,"passed_time":36.97540713,"remaining_time":25.90793833},
{"learn":[0.004405374526],"iteration":588,"passed_time":37.0134931,"remaining_time":25.82775155},
{"learn":[0.00440537116],"iteration":589,"passed_time":37.06653944,"remaining_time":25.75810368},
{"learn":[0.004405367797],"iteration":590,"passed_time":37.11720222,"remaining_time":25.68686245},
{"learn":[0.004405357151],"iteration":591,"passed_time":37.16925631,"remaining_time":25.61664962},
{"learn":[0.00440535443],"iteration":592,"passed_time":37.24503757,"remaining_time":25.56278295},
{"learn":[0.004405347712],"iteration":593,"passed_time":37.30171814,"remaining_time":25.49578714},
{"learn":[0.004405339308],"iteration":594,"passed_time":37.37747072,"remaining_time":25.4418078},
{"learn":[0.004405338888],"iteration":595,"passed_time":37.42208545,"remaining_time":25.36664853},
{"learn":[0.004405328244],"iteration":596,"passed_time":37.4789075,"remaining_time":25.29983203},
{"learn":[0.004405326567],"iteration":597,"passed_time":37.53917343,"remaining_time":25.23536408},
{"learn":[0.004405321257],"iteration":598,"passed_time":37.59446222,"remaining_time":25.16757821},
{"learn":[0.00440531958],"iteration":599,"passed_time":37.64442453,"remaining_time":25.09628302},
{"learn":[0.004405317904],"iteration":600,"passed_time":37.69002423,"remaining_time":25.02216251},
{"learn":[0.004405309502],"iteration":601,"passed_time":37.73511565,"remaining_time":24.94780071},
{"learn":[0.004405301103],"iteration":602,"passed_time":37.78848671,"remaining_time":24.8789871},
{"learn":[0.004405299428],"iteration":603,"passed_time":37.83933275,"remaining_time":24.80856915},
{"learn":[0.004405294121],"iteration":604,"passed_time":37.87792929,"remaining_time":24.73021829},
{"learn":[0.004405252184],"iteration":605,"passed_time":37.91393278,"remaining_time":24.65031273},
{"learn":[0.004405250861],"iteration":606,"passed_time":37.95209344,"remaining_time":24.57194847},
{"learn":[0.004405242463],"iteration":607,"passed_time":37.98706216,"remaining_time":24.4916585},
{"learn":[0.00440524114],"iteration":608,"passed_time":38.01982102,"remaining_time":24.41009856},
{"learn":[0.004405237796],"iteration":609,"passed_time":38.05303229,"remaining_time":24.32898786},
{"learn":[0.004405237135],"iteration":610,"passed_time":38.08760107,"remaining_time":24.24889823},
{"learn":[0.004405230452],"iteration":611,"passed_time":38.14665845,"remaining_time":24.18448281},
{"learn":[0.004405222057],"iteration":612,"passed_time":38.20755516,"remaining_time":24.12124608},
{"learn":[0.00440522164],"iteration":613,"passed_time":38.24258597,"remaining_time":24.041756},
{"learn":[0.004405213248],"iteration":614,"passed_time":38.29049217,"remaining_time":23.97047071},
{"learn":[0.00440521115],"iteration":615,"passed_time":38.36845847,"remaining_time":23.91800008},
{"learn":[0.004405209053],"iteration":616,"passed_time":38.42514265,"remaining_time":23.85223604},
{"learn":[0.004405206956],"iteration":617,"passed_time":38.505896,"remaining_time":23.80137908},
{"learn":[0.004405203618],"iteration":618,"passed_time":38.56521161,"remaining_time":23.73723041},
{"learn":[0.004405201521],"iteration":619,"passed_time":38.6006717,"remaining_time":23.6584762},
{"learn":[0.004405199424],"iteration":620,"passed_time":38.65856872,"remaining_time":23.59355482},
{"learn":[0.004405197328],"iteration":621,"passed_time":38.69339427,"remaining_time":23.5146351},
{"learn":[0.004405196667],"iteration":622,"passed_time":38.74124114,"remaining_time":23.44373661},
{"learn":[0.00440519457],"iteration":623,"passed_time":38.78600977,"remaining_time":23.37105717},
{"learn":[0.004405194153],"iteration":624,"passed_time":38.8429603,"remaining_time":23.30577618},
{"learn":[0.004405192057],"iteration":625,"passed_time":38.88112613,"remaining_time":23.229299},
{"learn":[0.00440519164],"iteration":626,"passed_time":38.95084192,"remaining_time":23.17171297},
{"learn":[0.004405189544],"iteration":627,"passed_time":38.99006088,"remaining_time":23.09602333},
{"learn":[0.004405187448],"iteration":628,"passed_time":39.03164619,"remaining_time":23.02184537},
{"learn":[0.004405187032],"iteration":629,"passed_time":39.07817006,"remaining_time":22.95067131},
{"learn":[0.004405184936],"iteration":630,"passed_time":39.16740944,"remaining_time":22.90455481},
{"learn":[0.004405182296],"iteration":631,"passed_time":39.23455832,"remaining_time":22.84543902},
{"learn":[0.004405181462],"iteration":632,"passed_time":39.30727039,"remaining_time":22.78952328},
{"learn":[0.004405179367],"iteration":633,"passed_time":39.35676102,"remaining_time":22.7201491},
{"learn":[0.004405177271],"iteration":634,"passed_time":39.40286113,"remaining_time":22.64888868},
{"learn":[0.004405175176],"iteration":635,"passed_time":39.45786872,"remaining_time":22.58280537},
{"learn":[0.004405172537],"iteration":636,"passed_time":39.49588084,"remaining_time":22.50707181},
{"learn":[0.004405171703],"iteration":637,"passed_time":39.58069015,"remaining_time":22.45800914},
{"learn":[0.004405169608],"iteration":638,"passed_time":39.62654491,"remaining_time":22.3868274},
{"learn":[0.004405167513],"iteration":639,"passed_time":39.67124052,"remaining_time":22.31507279},
{"learn":[0.004405165419],"iteration":640,"passed_time":39.70844408,"remaining_time":22.23920659},
{"learn":[0.004405163324],"iteration":641,"passed_time":39.76499772,"remaining_time":22.17425107},
{"learn":[0.00440516123],"iteration":642,"passed_time":39.81160532,"remaining_time":22.10379953},
{"learn":[0.004405160397],"iteration":643,"passed_time":39.8591979,"remaining_time":22.03396654},
{"learn":[0.004405159736],"iteration":644,"passed_time":39.91274412,"remaining_time":21.96747932},
{"learn":[0.004405159077],"iteration":645,"passed_time":39.95626591,"remaining_time":21.8955389},
{"learn":[0.004405158243],"iteration":646,"passed_time":40.00540748,"remaining_time":21.82675246},
{"learn":[0.00440515741],"iteration":647,"passed_time":40.0591335,"remaining_time":21.76051696},
{"learn":[0.004405155316],"iteration":648,"passed_time":40.10944374,"remaining_time":21.69247266},
{"learn":[0.004405093027],"iteration":649,"passed_time":40.18184201,"remaining_time":21.63637647},
{"learn":[0.004405089702],"iteration":650,"passed_time":40.22784431,"remaining_time":21.56607936},
{"learn":[0.004405084458],"iteration":651,"passed_time":40.26347865,"remaining_time":21.49032296},
{"learn":[0.004405077815],"iteration":652,"passed_time":40.30473937,"remaining_time":21.41767927},
{"learn":[0.004405067336],"iteration":653,"passed_time":40.33822833,"remaining_time":21.34101988},
{"learn":[0.004405065241],"iteration":654,"passed_time":40.37357773,"remaining_time":21.26547224},
{"learn":[0.004405063582],"iteration":655,"passed_time":40.41875657,"remaining_time":21.19520161},
{"learn":[0.004405001779],"iteration":656,"passed_time":40.46263271,"remaining_time":21.12432727},
{"learn":[0.004404991121],"iteration":657,"passed_time":40.52325837,"remaining_time":21.06224067},
{"learn":[0.004404982741],"iteration":658,"passed_time":40.59733125,"remaining_time":21.00711678},
{"learn":[0.004404976129],"iteration":659,"passed_time":40.64751314,"remaining_time":20.93962798},
{"learn":[0.004404975303],"iteration":660,"passed_time":40.70841122,"remaining_time":20.87768745},
{"learn":[0.004404971114],"iteration":661,"passed_time":40.75618505,"remaining_time":20.80904917},
{"learn":[0.004404970289],"iteration":662,"passed_time":40.8277057,"remaining_time":20.75254423},
{"learn":[0.004404970289],"iteration":663,"passed_time":40.86218271,"remaining_time":20.67724908},
{"learn":[0.004404970289],"iteration":664,"passed_time":40.92117687,"remaining_time":20.61442744},
{"learn":[0.004404965084],"iteration":665,"passed_time":40.95661491,"remaining_time":20.53980388},
{"learn":[0.004404960896],"iteration":666,"passed_time":41.01643517,"remaining_time":20.47747063},
{"learn":[0.004404959432],"iteration":667,"passed_time":41.07838858,"remaining_time":20.4162051},
{"learn":[0.004404958606],"iteration":668,"passed_time":41.14539561,"remaining_time":20.35743789},
{"learn":[0.004404956512],"iteration":669,"passed_time":41.19034527,"remaining_time":20.287782},
{"learn":[0.004404461366],"iteration":670,"passed_time":41.25327258,"remaining_time":20.22701443},
{"learn":[0.004404452976],"iteration":671,"passed_time":41.30645143,"remaining_time":20.16148225},
{"learn":[0.004404446472],"iteration":672,"passed_time":41.3530095,"remaining_time":20.09276984},
{"learn":[0.004404225277],"iteration":673,"passed_time":41.3897631,"remaining_time":20.01938097},
{"learn":[0.004403942832],"iteration":674,"passed_time":41.46691732,"remaining_time":19.96555278},
{"learn":[0.004403936459],"iteration":675,"passed_time":41.51848204,"remaining_time":19.8993908},
{"learn":[0.004403919649],"iteration":676,"passed_time":41.56019228,"remaining_time":19.82857032},
{"learn":[0.004403913705],"iteration":677,"passed_time":41.61863042,"remaining_time":19.76578023},
{"learn":[0.004403907338],"iteration":678,"passed_time":41.67887359,"remaining_time":19.70385629},
{"learn":[0.004403890539],"iteration":679,"passed_time":41.7307521,"remaining_time":19.63800099},
{"learn":[0.004403873751],"iteration":680,"passed_time":41.77247283,"remaining_time":19.56742853},
{"learn":[0.004403865363],"iteration":681,"passed_time":41.83141442,"remaining_time":19.50497036},
{"learn":[0.004403864568],"iteration":682,"passed_time":41.87895983,"remaining_time":19.43723319},
{"learn":[0.004403856182],"iteration":683,"passed_time":41.95755658,"remaining_time":19.38390041},
{"learn":[0.004403855387],"iteration":684,"passed_time":42.03428486,"remaining_time":19.32963464},
{"learn":[0.004403853291],"iteration":685,"passed_time":42.07043784,"remaining_time":19.25673102},
{"learn":[0.004403844909],"iteration":686,"passed_time":42.10570595,"remaining_time":19.18353124},
{"learn":[0.00440383653],"iteration":687,"passed_time":42.15473507,"remaining_time":19.11668219},
{"learn":[0.004403828154],"iteration":688,"passed_time":42.18742661,"remaining_time":19.04251041},
{"learn":[0.004403828154],"iteration":689,"passed_time":42.23287116,"remaining_time":18.97418849},
{"learn":[0.004403828154],"iteration":690,"passed_time":42.28132739,"remaining_time":18.90727954},
{"learn":[0.004403827359],"iteration":691,"passed_time":42.36763121,"remaining_time":18.85726938},
{"learn":[0.004403826565],"iteration":692,"passed_time":42.44149193,"remaining_time":18.80164217},
{"learn":[0.004403771036],"iteration":693,"passed_time":42.49051771,"remaining_time":18.73501213},
{"learn":[0.004403754286],"iteration":694,"passed_time":42.54807046,"remaining_time":18.67217481},
{"learn":[0.004403754286],"iteration":695,"passed_time":42.58275762,"remaining_time":18.5993654},
{"learn":[0.004403745916],"iteration":696,"passed_time":42.63963238,"remaining_time":18.53631078},
{"learn":[0.004403745916],"iteration":697,"passed_time":42.67407445,"remaining_time":18.46356803},
{"learn":[0.004403745916],"iteration":698,"passed_time":42.7470362,"remaining_time":18.40752203},
{"learn":[0.004403734245],"iteration":699,"passed_time":42.79096027,"remaining_time":18.33898297},
{"learn":[0.004403734245],"iteration":700,"passed_time":42.83822577,"remaining_time":18.27193938},
{"learn":[0.00440372258],"iteration":701,"passed_time":42.87533261,"remaining_time":18.20063977},
{"learn":[0.004403714213],"iteration":702,"passed_time":42.91103388,"remaining_time":18.12884362},
{"learn":[0.004403714213],"iteration":703,"passed_time":42.9585678,"remaining_time":18.0621251},
{"learn":[0.004403705848],"iteration":704,"passed_time":42.99142757,"remaining_time":17.98932076},
{"learn":[0.004403701173],"iteration":705,"passed_time":43.05254693,"remaining_time":17.92839773},
{"learn":[0.004403628083],"iteration":706,"passed_time":43.11306717,"remaining_time":17.86722585},
{"learn":[0.004403618785],"iteration":707,"passed_time":43.14859689,"remaining_time":17.795749},
{"learn":[0.004403617203],"iteration":708,"passed_time":43.18334403,"remaining_time":17.72405235},
{"learn":[0.004403615621],"iteration":709,"passed_time":43.2232036,"remaining_time":17.65454795},
{"learn":[0.004403598892],"iteration":710,"passed_time":43.27077246,"remaining_time":17.58826053},
{"learn":[0.004402947344],"iteration":711,"passed_time":43.31958102,"remaining_time":17.52252716},
{"learn":[0.004402944256],"iteration":712,"passed_time":43.37372049,"remaining_time":17.45898707},
{"learn":[0.004402935879],"iteration":713,"passed_time":43.40862638,"remaining_time":17.38776911},
{"learn":[0.004402927506],"iteration":714,"passed_time":43.49515003,"remaining_time":17.33722763},
{"learn":[0.004402884122],"iteration":715,"passed_time":43.53256924,"remaining_time":17.26710847},
{"learn":[0.004402881024],"iteration":716,"passed_time":43.59646322,"remaining_time":17.20753011},
{"learn":[0.004402863605],"iteration":717,"passed_time":43.65159526,"remaining_time":17.14449842},
{"learn":[0.004402863605],"iteration":718,"passed_time":43.70445388,"remaining_time":17.0806002},
{"learn":[0.00440283012],"iteration":719,"passed_time":43.74979227,"remaining_time":17.0138081},
{"learn":[0.004402821758],"iteration":720,"passed_time":43.79566232,"remaining_time":16.94728126},
{"learn":[0.004402821372],"iteration":721,"passed_time":43.85534403,"remaining_time":16.8861297},
{"learn":[0.004402787945],"iteration":722,"passed_time":43.89402776,"remaining_time":16.81693733},
{"learn":[0.004402779597],"iteration":723,"passed_time":43.97664003,"remaining_time":16.76457548},
{"learn":[0.004402773411],"iteration":724,"passed_time":44.0213343,"remaining_time":16.69774749},
{"learn":[0.004402765067],"iteration":725,"passed_time":44.06793898,"remaining_time":16.63170149},
{"learn":[0.004402747653],"iteration":726,"passed_time":44.11479266,"remaining_time":16.56580247},
{"learn":[0.004402746108],"iteration":727,"passed_time":44.17542032,"remaining_time":16.5051021},
{"learn":[0.004402746108],"iteration":728,"passed_time":44.21092134,"remaining_time":16.43506129},
{"learn":[0.004402744564],"iteration":729,"passed_time":44.27025871,"remaining_time":16.3739313},
{"learn":[0.004402743021],"iteration":730,"passed_time":44.33107533,"remaining_time":16.31335056},
{"learn":[0.004402741478],"iteration":731,"passed_time":44.40721497,"remaining_time":16.25837925},
{"learn":[0.004402739392],"iteration":732,"passed_time":44.44321071,"remaining_time":16.1887275},
{"learn":[0.004402735221],"iteration":733,"passed_time":44.50566539,"remaining_time":16.12875612},
{"learn":[0.004402733679],"iteration":734,"passed_time":44.56888721,"remaining_time":16.06905457},
{"learn":[0.004402727511],"iteration":735,"passed_time":44.60815012,"remaining_time":16.0007495},
{"learn":[0.004402725426],"iteration":736,"passed_time":44.67107276,"remaining_time":15.94096626},
{"learn":[0.004402724341],"iteration":737,"passed_time":44.7314545,"remaining_time":15.88027246},
{"learn":[0.004402718181],"iteration":738,"passed_time":44.789497,"remaining_time":15.81875334},
{"learn":[0.004402716642],"iteration":739,"passed_time":44.86386732,"remaining_time":15.76298041},
{"learn":[0.004402714557],"iteration":740,"passed_time":44.90897607,"remaining_time":15.69692956},
{"learn":[0.004402708709],"iteration":741,"passed_time":44.95252485,"remaining_time":15.63039274},
{"learn":[0.004402707623],"iteration":742,"passed_time":45.01411857,"remaining_time":15.57015945},
{"learn":[0.004402706539],"iteration":743,"passed_time":45.07271229,"remaining_time":15.50889025},
{"learn":[0.004402703462],"iteration":744,"passed_time":45.1470763,"remaining_time":15.45302612},
{"learn":[0.004402700387],"iteration":745,"passed_time":45.18152786,"remaining_time":15.38352289},
{"learn":[0.004402683047],"iteration":746,"passed_time":45.2388606,"remaining_time":15.32186309},
{"learn":[0.004402674381],"iteration":747,"passed_time":45.27391195,"remaining_time":15.2527083},
{"learn":[0.00440266824],"iteration":748,"passed_time":45.32081433,"remaining_time":15.18761602},
{"learn":[0.004402475178],"iteration":749,"passed_time":45.37030067,"remaining_time":15.12343356},
{"learn":[0.004402474417],"iteration":750,"passed_time":45.454863,"remaining_time":15.07091995},
{"learn":[0.004402440956],"iteration":751,"passed_time":45.49211178,"remaining_time":15.00271771},
{"learn":[0.004402428956],"iteration":752,"passed_time":45.5611627,"remaining_time":14.94502946},
{"learn":[0.004402428428],"iteration":753,"passed_time":45.64123754,"remaining_time":14.89090774},
{"learn":[0.004402428428],"iteration":754,"passed_time":45.68659272,"remaining_time":14.82545062},
{"learn":[0.004402420077],"iteration":755,"passed_time":45.74210179,"remaining_time":14.76332386},
{"learn":[0.004402386698],"iteration":756,"passed_time":45.78539138,"remaining_time":14.69729208},
{"learn":[0.004402380611],"iteration":757,"passed_time":45.90322529,"remaining_time":14.65511942},
{"learn":[0.004401974048],"iteration":758,"passed_time":45.94978556,"remaining_time":14.59011636},
{"learn":[0.004401972546],"iteration":759,"passed_time":46.00930757,"remaining_time":14.52925502},
{"learn":[0.004401968513],"iteration":760,"passed_time":46.06110398,"remaining_time":14.46597089},
{"learn":[0.004401962649],"iteration":761,"passed_time":46.11042012,"remaining_time":14.40194224},
{"learn":[0.004401958617],"iteration":762,"passed_time":46.16507992,"remaining_time":14.33961198},
{"learn":[0.004401957116],"iteration":763,"passed_time":46.21199586,"remaining_time":14.27490972},
{"learn":[0.004394711944],"iteration":764,"passed_time":46.26617925,"remaining_time":14.21248644},
{"learn":[0.004394706303],"iteration":765,"passed_time":46.31534412,"remaining_time":14.1485516},
{"learn":[0.004394698188],"iteration":766,"passed_time":46.36961443,"remaining_time":14.08620621},
{"learn":[0.004394696106],"iteration":767,"passed_time":46.44996829,"remaining_time":14.03176125},
{"learn":[0.004394694023],"iteration":768,"passed_time":46.5233788,"remaining_time":13.9751632},
{"learn":[0.004394691941],"iteration":769,"passed_time":46.56972927,"remaining_time":13.91043861},
{"learn":[0.004394690406],"iteration":770,"passed_time":46.62761683,"remaining_time":13.8491884},
{"learn":[0.004394642537],"iteration":771,"passed_time":46.66232441,"remaining_time":13.78110099},
{"learn":[0.004394626415],"iteration":772,"passed_time":46.7228017,"remaining_time":13.72066751},
{"learn":[0.004394446607],"iteration":773,"passed_time":46.76956513,"remaining_time":13.65622961},
{"learn":[0.0043943851],"iteration":774,"passed_time":46.8329901,"remaining_time":13.59667455},
{"learn":[0.004394376758],"iteration":775,"passed_time":46.88412933,"remaining_time":13.5335631},
{"learn":[0.004394374801],"iteration":776,"passed_time":46.92564627,"remaining_time":13.46772087},
{"learn":[0.004394372843],"iteration":777,"passed_time":46.97204147,"remaining_time":13.40333317},
{"learn":[0.004394372083],"iteration":778,"passed_time":47.02124063,"remaining_time":13.33978714},
{"learn":[0.004394371323],"iteration":779,"passed_time":47.07671671,"remaining_time":13.2780483},
{"learn":[0.004394362984],"iteration":780,"passed_time":47.12398049,"remaining_time":13.2140227},
{"learn":[0.004394361027],"iteration":781,"passed_time":47.15879393,"remaining_time":13.14656915},
{"learn":[0.004394353203],"iteration":782,"passed_time":47.20601662,"remaining_time":13.08263807},
{"learn":[0.004394345387],"iteration":783,"passed_time":47.26550164,"remaining_time":13.022128},
{"learn":[0.004394299267],"iteration":784,"passed_time":47.31199321,"remaining_time":12.95806184},
{"learn":[0.0043942932],"iteration":785,"passed_time":47.37057361,"remaining_time":12.89733175},
{"learn":[0.004394284861],"iteration":786,"passed_time":47.40593474,"remaining_time":12.83032287},
{"learn":[0.004394284103],"iteration":787,"passed_time":47.45234161,"remaining_time":12.76636602},
{"learn":[0.004394272321],"iteration":788,"passed_time":47.58774073,"remaining_time":12.72625259},
{"learn":[0.004394256792],"iteration":789,"passed_time":47.63589334,"remaining_time":12.66270583},
{"learn":[0.004394248453],"iteration":790,"passed_time":47.68473115,"remaining_time":12.59937903},
{"learn":[0.004394246515],"iteration":791,"passed_time":47.74082413,"remaining_time":12.53799422},
{"learn":[0.004394130866],"iteration":792,"passed_time":47.80207592,"remaining_time":12.47796938},
{"learn":[0.004394114164],"iteration":793,"passed_time":47.86172735,"remaining_time":12.41752624},
{"learn":[0.004394111121],"iteration":794,"passed_time":47.92601185,"remaining_time":12.35827979},
{"learn":[0.00439410808],"iteration":795,"passed_time":47.99040933,"remaining_time":12.29904963},
{"learn":[0.004394047505],"iteration":796,"passed_time":48.02279043,"remaining_time":12.23165177},
{"learn":[0.004394043656],"iteration":797,"passed_time":48.05651654,"remaining_time":12.16468213},
{"learn":[0.00439403759],"iteration":798,"passed_time":48.13151232,"remaining_time":12.10817769},
{"learn":[0.004394031531],"iteration":799,"passed_time":48.19128411,"remaining_time":12.04782103},
{"learn":[0.004393986103],"iteration":800,"passed_time":48.2238502,"remaining_time":11.98070685},
{"learn":[0.004393952706],"iteration":801,"passed_time":48.25756246,"remaining_time":11.91396181},
{"learn":[0.004393936029],"iteration":802,"passed_time":48.3321951,"remaining_time":11.85733803},
{"learn":[0.004393933007],"iteration":803,"passed_time":48.38309849,"remaining_time":11.79488471},
{"learn":[0.004393931093],"iteration":804,"passed_time":48.42780354,"remaining_time":11.73095862},
{"learn":[0.004393928073],"iteration":805,"passed_time":48.50220351,"remaining_time":11.67422764},
{"learn":[0.004393868297],"iteration":806,"passed_time":48.53599723,"remaining_time":11.60774159},
{"learn":[0.004393866212],"iteration":807,"passed_time":48.57005169,"remaining_time":11.54139842},
{"learn":[0.004393864128],"iteration":808,"passed_time":48.6134853,"remaining_time":11.47734943},
{"learn":[0.00439386033],"iteration":809,"passed_time":48.64969391,"remaining_time":11.4116566},
{"learn":[0.004393845166],"iteration":810,"passed_time":48.6887397,"remaining_time":11.34669766},
{"learn":[0.004393828494],"iteration":811,"passed_time":48.73654678,"remaining_time":11.28383103},
{"learn":[0.004393824396],"iteration":812,"passed_time":48.77298534,"remaining_time":11.21838654},
{"learn":[0.00439381682],"iteration":813,"passed_time":48.82766266,"remaining_time":11.1571809},
{"learn":[0.00439380925],"iteration":814,"passed_time":48.91320714,"remaining_time":11.10299794},
{"learn":[0.004393263575],"iteration":815,"passed_time":48.94862198,"remaining_time":11.03743437},
{"learn":[0.004393246882],"iteration":816,"passed_time":48.99583203,"remaining_time":10.97458661},
{"learn":[0.0043932302],"iteration":817,"passed_time":49.04315005,"remaining_time":10.91180111},
{"learn":[0.004393223044],"iteration":818,"passed_time":49.08860678,"remaining_time":10.84864204},
{"learn":[0.004393217127],"iteration":819,"passed_time":49.16216612,"remaining_time":10.791695},
{"learn":[0.004393215648],"iteration":820,"passed_time":49.19640716,"remaining_time":10.72613506},
{"learn":[0.004392598738],"iteration":821,"passed_time":49.25561198,"remaining_time":10.6660571},
{"learn":[0.004392448768],"iteration":822,"passed_time":49.29585229,"remaining_time":10.60190262},
{"learn":[0.004383693397],"iteration":823,"passed_time":49.36059032,"remaining_time":10.54303871},
{"learn":[0.004383685878],"iteration":824,"passed_time":49.39971576,"remaining_time":10.47872758},
{"learn":[0.004383670855],"iteration":825,"passed_time":49.46173833,"remaining_time":10.41930081},
{"learn":[0.00438197436],"iteration":826,"passed_time":49.51795053,"remaining_time":10.35865229},
{"learn":[0.004381962157],"iteration":827,"passed_time":49.56461857,"remaining_time":10.29603188},
{"learn":[0.004378468539],"iteration":828,"passed_time":49.62417607,"remaining_time":10.23610869},
{"learn":[0.00437013123],"iteration":829,"passed_time":49.70277948,"remaining_time":10.18008736},
{"learn":[0.004363203835],"iteration":830,"passed_time":49.7628045,"remaining_time":10.12023341},
{"learn":[0.004363201771],"iteration":831,"passed_time":49.85283968,"remaining_time":10.06643878},
{"learn":[0.00435022206],"iteration":832,"passed_time":49.93624674,"remaining_time":10.01122834},
{"learn":[0.004350218131],"iteration":833,"passed_time":50.01136522,"remaining_time":9.954300512},
{"learn":[0.004323317464],"iteration":834,"passed_time":50.09207054,"remaining_time":9.898433101},
{"learn":[0.004323316625],"iteration":835,"passed_time":50.1271482,"remaining_time":9.833555388},
{"learn":[0.004315539121],"iteration":836,"passed_time":50.1968057,"remaining_time":9.775483069},
{"learn":[0.004309510022],"iteration":837,"passed_time":50.25772948,"remaining_time":9.715694721},
{"learn":[0.004309510022],"iteration":838,"passed_time":50.3103377,"remaining_time":9.654307949},
{"learn":[0.004297502851],"iteration":839,"passed_time":50.36586682,"remaining_time":9.593498441},
{"learn":[0.004297500154],"iteration":840,"passed_time":50.46254742,"remaining_time":9.540481617},
{"learn":[0.004292543077],"iteration":841,"passed_time":50.50838468,"remaining_time":9.477820403},
{"learn":[0.004292539968],"iteration":842,"passed_time":50.56509525,"remaining_time":9.417224145},
{"learn":[0.004287829106],"iteration":843,"passed_time":50.65294291,"remaining_time":9.362392291},
{"learn":[0.004287828286],"iteration":844,"passed_time":50.68776221,"remaining_time":9.297755198},
{"learn":[0.004287819911],"iteration":845,"passed_time":50.75390752,"remaining_time":9.238890966},
{"learn":[0.004287819133],"iteration":846,"passed_time":50.80846017,"remaining_time":9.177915473},
{"learn":[0.004287818355],"iteration":847,"passed_time":50.84872569,"remaining_time":9.114394228},
{"learn":[0.004287817577],"iteration":848,"passed_time":50.90060611,"remaining_time":9.052993548},
{"learn":[0.0042878168],"iteration":849,"passed_time":50.93515374,"remaining_time":8.988556543},
{"learn":[0.004287816022],"iteration":850,"passed_time":50.99811996,"remaining_time":8.92916554},
{"learn":[0.004287815202],"iteration":851,"passed_time":51.04608617,"remaining_time":8.867160508},
{"learn":[0.004287814383],"iteration":852,"passed_time":51.12482167,"remaining_time":8.810490955},
{"learn":[0.004287813563],"iteration":853,"passed_time":51.16485604,"remaining_time":8.747153375},
{"learn":[0.004287812743],"iteration":854,"passed_time":51.21108192,"remaining_time":8.684920326},
{"learn":[0.004287811966],"iteration":855,"passed_time":51.29138661,"remaining_time":8.62845756},
{"learn":[0.004287811189],"iteration":856,"passed_time":51.35035659,"remaining_time":8.568379221},
{"learn":[0.0042867471],"iteration":857,"passed_time":51.40644281,"remaining_time":8.5078262},
{"learn":[0.004286740915],"iteration":858,"passed_time":51.46010907,"remaining_time":8.446886355},
{"learn":[0.004282266761],"iteration":859,"passed_time":51.50229353,"remaining_time":8.384094295},
{"learn":[0.00427624472],"iteration":860,"passed_time":51.58182791,"remaining_time":8.327379883},
{"learn":[0.004276238141],"iteration":861,"passed_time":51.61917482,"remaining_time":8.263858614},
{"learn":[0.004265004896],"iteration":862,"passed_time":51.68953517,"remaining_time":8.205638839},
{"learn":[0.004265004112],"iteration":863,"passed_time":51.74320974,"remaining_time":8.144764497},
{"learn":[0.004264996393],"iteration":864,"passed_time":51.80068547,"remaining_time":8.084500045},
{"learn":[0.004264990113],"iteration":865,"passed_time":51.84256168,"remaining_time":8.02182825},
{"learn":[0.004264987011],"iteration":866,"passed_time":51.90942778,"remaining_time":7.963037941},
{"learn":[0.004264985085],"iteration":867,"passed_time":51.97058175,"remaining_time":7.903360359},
{"learn":[0.004264981954],"iteration":868,"passed_time":52.04015575,"remaining_time":7.84494868},
{"learn":[0.004264980991],"iteration":869,"passed_time":52.09838958,"remaining_time":7.784816833},
{"learn":[0.004264977893],"iteration":870,"passed_time":52.1401404,"remaining_time":7.72224812},
{"learn":[0.004264975968],"iteration":871,"passed_time":52.22762313,"remaining_time":7.666440092},
{"learn":[0.00426497442],"iteration":872,"passed_time":52.27849183,"remaining_time":7.60523306},
{"learn":[0.004264972872],"iteration":873,"passed_time":52.36812024,"remaining_time":7.549637472},
{"learn":[0.004235619844],"iteration":874,"passed_time":52.428216,"remaining_time":7.489745144},
{"learn":[0.004235618939],"iteration":875,"passed_time":52.47959787,"remaining_time":7.428618876},
{"learn":[0.004235618162],"iteration":876,"passed_time":52.5272912,"remaining_time":7.366997511},
{"learn":[0.004235617384],"iteration":877,"passed_time":52.5603609,"remaining_time":7.303375888},
{"learn":[0.004217532468],"iteration":878,"passed_time":52.63114896,"remaining_time":7.245015955},
{"learn":[0.004217531762],"iteration":879,"passed_time":52.66859574,"remaining_time":7.182081237},
{"learn":[0.004217530928],"iteration":880,"passed_time":52.7392745,"remaining_time":7.123693151},
{"learn":[0.004217527692],"iteration":881,"passed_time":52.78852964,"remaining_time":7.062410995},
{"learn":[0.004217526858],"iteration":882,"passed_time":52.86516837,"remaining_time":7.004784484},
{"learn":[0.004203439219],"iteration":883,"passed_time":52.93872419,"remaining_time":6.946710414},
{"learn":[0.004203436196],"iteration":884,"passed_time":52.99095989,"remaining_time":6.885830946},
{"learn":[0.004203435403],"iteration":885,"passed_time":53.08138364,"remaining_time":6.829884577},
{"learn":[0.004186536857],"iteration":886,"passed_time":53.17241388,"remaining_time":6.773937732},
{"learn":[0.004181147003],"iteration":887,"passed_time":53.24976527,"remaining_time":6.716186611},
{"learn":[0.004181140912],"iteration":888,"passed_time":53.33913893,"remaining_time":6.659892487},
{"learn":[0.004168044803],"iteration":889,"passed_time":53.41220686,"remaining_time":6.601508714},
{"learn":[0.004168039955],"iteration":890,"passed_time":53.48588252,"remaining_time":6.543166324},
{"learn":[0.004168033547],"iteration":891,"passed_time":53.56369573,"remaining_time":6.485290515},
{"learn":[0.004152281559],"iteration":892,"passed_time":53.62352412,"remaining_time":6.425215096},
{"learn":[0.004146790528],"iteration":893,"passed_time":53.68058237,"remaining_time":6.36481178},
{"learn":[0.004146790102],"iteration":894,"passed_time":53.72936929,"remaining_time":6.303445559},
{"learn":[0.004146789676],"iteration":895,"passed_time":53.78647691,"remaining_time":6.243073213},
{"learn":[0.004134896193],"iteration":896,"passed_time":53.86161702,"remaining_time":6.184778766},
{"learn":[0.004134895401],"iteration":897,"passed_time":53.90294372,"remaining_time":6.122606079},
{"learn":[0.004134894537],"iteration":898,"passed_time":53.95707022,"remaining_time":6.061917789},
{"learn":[0.004120061089],"iteration":899,"passed_time":53.99797832,"remaining_time":5.999775369},
{"learn":[0.004105995537],"iteration":900,"passed_time":54.05700047,"remaining_time":5.939670418},
{"learn":[0.004105995087],"iteration":901,"passed_time":54.12070101,"remaining_time":5.880076163},
{"learn":[0.004105991635],"iteration":902,"passed_time":54.18278355,"remaining_time":5.820299008},
{"learn":[0.004093950519],"iteration":903,"passed_time":54.22815223,"remaining_time":5.75874183},
{"learn":[0.004093943281],"iteration":904,"passed_time":54.27146963,"remaining_time":5.6970051},
{"learn":[0.004078662678],"iteration":905,"passed_time":54.34350726,"remaining_time":5.638288833},
{"learn":[0.004078661968],"iteration":906,"passed_time":54.3944487,"remaining_time":5.577380076},
{"learn":[0.004078658407],"iteration":907,"passed_time":54.42700392,"remaining_time":5.514630353},
{"learn":[0.004078657953],"iteration":908,"passed_time":54.48237674,"remaining_time":5.454231334},
{"learn":[0.004065341547],"iteration":909,"passed_time":54.54166221,"remaining_time":5.394230328},
{"learn":[0.004065301392],"iteration":910,"passed_time":54.58958413,"remaining_time":5.333120733},
{"learn":[0.004065297726],"iteration":911,"passed_time":54.62869895,"remaining_time":5.271190249},
{"learn":[0.004053999083],"iteration":912,"passed_time":54.69734815,"remaining_time":5.212124085},
{"learn":[0.004045466778],"iteration":913,"passed_time":54.75635679,"remaining_time":5.152129851},
{"learn":[0.004029242428],"iteration":914,"passed_time":54.81561779,"remaining_time":5.092161215},
{"learn":[0.004029235791],"iteration":915,"passed_time":54.87260169,"remaining_time":5.031985308},
{"learn":[0.00401586511],"iteration":916,"passed_time":54.94397806,"remaining_time":4.973119061},
{"learn":[0.004015856819],"iteration":917,"passed_time":54.99183651,"remaining_time":4.91212483},
{"learn":[0.004015856],"iteration":918,"passed_time":55.04415812,"remaining_time":4.851552565},
{"learn":[0.004015852721],"iteration":919,"passed_time":55.10565442,"remaining_time":4.791796036},
{"learn":[0.004015848775],"iteration":920,"passed_time":55.1427434,"remaining_time":4.729942159},
{"learn":[0.004015840879],"iteration":921,"passed_time":55.19724376,"remaining_time":4.669614982},
{"learn":[0.004012985031],"iteration":922,"passed_time":55.25471767,"remaining_time":4.609548495},
{"learn":[0.004012983341],"iteration":923,"passed_time":55.32239918,"remaining_time":4.550327205},
{"learn":[0.004012981652],"iteration":924,"passed_time":55.36946549,"remaining_time":4.489416121},
{"learn":[0.004012979963],"iteration":925,"passed_time":55.42826313,"remaining_time":4.429472432},
{"learn":[0.004012976023],"iteration":926,"passed_time":55.49071368,"remaining_time":4.369818877},
{"learn":[0.004005532312],"iteration":927,"passed_time":55.56449504,"remaining_time":4.311038408},
{"learn":[0.004005531953],"iteration":928,"passed_time":55.62036229,"remaining_time":4.250856537},
{"learn":[0.003995522071],"iteration":929,"passed_time":55.72794094,"remaining_time":4.1945762},
{"learn":[0.003995512899],"iteration":930,"passed_time":55.8256043,"remaining_time":4.137450802},
{"learn":[0.003991762969],"iteration":931,"passed_time":55.88625769,"remaining_time":4.077538115},
{"learn":[0.003991761074],"iteration":932,"passed_time":55.9238704,"remaining_time":4.015969257},
{"learn":[0.00399175918],"iteration":933,"passed_time":55.97812297,"remaining_time":3.955627533},
{"learn":[0.003991752274],"iteration":934,"passed_time":56.05225543,"remaining_time":3.896680859},
{"learn":[0.003989082558],"iteration":935,"passed_time":56.11849385,"remaining_time":3.837161972},
{"learn":[0.00398431403],"iteration":936,"passed_time":56.17621451,"remaining_time":3.777056045},
{"learn":[0.00398431403],"iteration":937,"passed_time":56.24607885,"remaining_time":3.717757877},
{"learn":[0.00398431403],"iteration":938,"passed_time":56.30772014,"remaining_time":3.657903012},
{"learn":[0.003984312135],"iteration":939,"passed_time":56.360359,"remaining_time":3.597469723},
{"learn":[0.003984312135],"iteration":940,"passed_time":56.42217186,"remaining_time":3.537628204},
{"learn":[0.003984312135],"iteration":941,"passed_time":56.47694094,"remaining_time":3.477348805},
{"learn":[0.00398431024],"iteration":942,"passed_time":56.51180242,"remaining_time":3.415877771},
{"learn":[0.00398431024],"iteration":943,"passed_time":56.57097041,"remaining_time":3.355905024},
{"learn":[0.00398431024],"iteration":944,"passed_time":56.60395081,"remaining_time":3.294409836},
{"learn":[0.00398431024],"iteration":945,"passed_time":56.64705233,"remaining_time":3.23355267},
{"learn":[0.003974940834],"iteration":946,"passed_time":56.70989909,"remaining_time":3.17383807},
{"learn":[0.003974940834],"iteration":947,"passed_time":56.76851634,"remaining_time":3.113884863},
{"learn":[0.003964662595],"iteration":948,"passed_time":56.82724738,"remaining_time":3.053940586},
{"learn":[0.003952171542],"iteration":949,"passed_time":56.91044803,"remaining_time":2.995286738},
{"learn":[0.003952164111],"iteration":950,"passed_time":56.95829342,"remaining_time":2.934759598},
{"learn":[0.003952149269],"iteration":951,"passed_time":57.02492066,"remaining_time":2.875206084},
{"learn":[0.003952147433],"iteration":952,"passed_time":57.07726044,"remaining_time":2.814933096},
{"learn":[0.003942099642],"iteration":953,"passed_time":57.13389132,"remaining_time":2.754883649},
{"learn":[0.003942097763],"iteration":954,"passed_time":57.20073277,"remaining_time":2.695322487},
{"learn":[0.003942082942],"iteration":955,"passed_time":57.23767852,"remaining_time":2.634370141},
{"learn":[0.003942081092],"iteration":956,"passed_time":57.28661486,"remaining_time":2.574006728},
{"learn":[0.003942066307],"iteration":957,"passed_time":57.32957515,"remaining_time":2.513405174},
{"learn":[0.003939618119],"iteration":958,"passed_time":57.39914675,"remaining_time":2.45397812},
{"learn":[0.003939614382],"iteration":959,"passed_time":57.46391241,"remaining_time":2.394329684},
{"learn":[0.003939612538],"iteration":960,"passed_time":57.5098529,"remaining_time":2.333906621},
{"learn":[0.003924604192],"iteration":961,"passed_time":57.57772761,"remaining_time":2.274380093},
{"learn":[0.00391311321],"iteration":962,"passed_time":57.64513051,"remaining_time":2.214818098},
{"learn":[0.003896825823],"iteration":963,"passed_time":57.70374664,"remaining_time":2.1549117},
{"learn":[0.003884123606],"iteration":964,"passed_time":57.76708659,"remaining_time":2.095179306},
{"learn":[0.003873743522],"iteration":965,"passed_time":57.82498239,"remaining_time":2.035247827},
{"learn":[0.003873740767],"iteration":966,"passed_time":57.89531286,"remaining_time":1.975744906},
{"learn":[0.003853059039],"iteration":967,"passed_time":57.96739974,"remaining_time":1.916277677},
{"learn":[0.00385305825],"iteration":968,"passed_time":58.01747757,"remaining_time":1.856080294},
{"learn":[0.003853054594],"iteration":969,"passed_time":58.05297543,"remaining_time":1.795452848},
{"learn":[0.003853054198],"iteration":970,"passed_time":58.11001221,"remaining_time":1.735520447},
{"learn":[0.003847515251],"iteration":971,"passed_time":58.1697603,"remaining_time":1.675672107},
{"learn":[0.003833708485],"iteration":972,"passed_time":58.22885933,"remaining_time":1.615805963},
{"learn":[0.003826548479],"iteration":973,"passed_time":58.29047985,"remaining_time":1.556008702},
{"learn":[0.003826548479],"iteration":974,"passed_time":58.3255769,"remaining_time":1.495527613},
{"learn":[0.003815524266],"iteration":975,"passed_time":58.40141686,"remaining_time":1.436100415},
{"learn":[0.003815523517],"iteration":976,"passed_time":58.45036437,"remaining_time":1.376006531},
{"learn":[0.003815519605],"iteration":977,"passed_time":58.49651991,"remaining_time":1.315872636},
{"learn":[0.003806290878],"iteration":978,"passed_time":58.55892359,"remaining_time":1.256115828},
{"learn":[0.003806290878],"iteration":979,"passed_time":58.59115668,"remaining_time":1.195737891},
{"learn":[0.003806290878],"iteration":980,"passed_time":58.65887693,"remaining_time":1.13610465},
{"learn":[0.003806290878],"iteration":981,"passed_time":58.69464564,"remaining_time":1.075869268},
{"learn":[0.003806289891],"iteration":982,"passed_time":58.72534,"remaining_time":1.015595911},
{"learn":[0.003799595441],"iteration":983,"passed_time":58.7822465,"remaining_time":0.9558088861},
{"learn":[0.003799592864],"iteration":984,"passed_time":58.83299732,"remaining_time":0.8959339694},
{"learn":[0.003792829876],"iteration":985,"passed_time":58.90516475,"remaining_time":0.8363816496},
{"learn":[0.003792814084],"iteration":986,"passed_time":58.93988289,"remaining_time":0.7763105143},
{"learn":[0.003783544078],"iteration":987,"passed_time":59.00713175,"remaining_time":0.7166858108},
{"learn":[0.003783540095],"iteration":988,"passed_time":59.04707704,"remaining_time":0.6567420096},
{"learn":[0.00378353371],"iteration":989,"passed_time":59.08059774,"remaining_time":0.5967737145},
{"learn":[0.00378353321],"iteration":990,"passed_time":59.12481258,"remaining_time":0.5369559164},
{"learn":[0.0037746393],"iteration":991,"passed_time":59.19203435,"remaining_time":0.4773551157},
{"learn":[0.003774628745],"iteration":992,"passed_time":59.23123861,"remaining_time":0.4175414605},
{"learn":[0.0037632308],"iteration":993,"passed_time":59.30749075,"remaining_time":0.3579929019},
{"learn":[0.003763222747],"iteration":994,"passed_time":59.34020976,"remaining_time":0.2981920088},
{"learn":[0.003754263961],"iteration":995,"passed_time":59.4002496,"remaining_time":0.2385552193},
{"learn":[0.003742078941],"iteration":996,"passed_time":59.46636025,"remaining_time":0.1789358884},
{"learn":[0.003742049839],"iteration":997,"passed_time":59.51572451,"remaining_time":0.119269989},
{"learn":[0.003742049336],"iteration":998,"passed_time":59.54597684,"remaining_time":0.05960558243},
{"learn":[0.003742041092],"iteration":999,"passed_time":59.60944776,"remaining_time":0}
]}